{
  "CEL0561": {
    "O": 0.75,
    "C": 0.73,
    "E": 0.65,
    "A": 0.23,
    "N": 0.74
  },
  "CRD0624": {
    "O": 0.4,
    "C": 0.3,
    "E": 0.17,
    "A": 0.73,
    "N": 0.51
  },
  "JFC0557": {
    "O": 0.3,
    "C": 0.15,
    "E": 0.33,
    "A": 0.75,
    "N": 0.54
  },
  "ASD0577": {
    "O": 0.75,
    "C": 0.95,
    "E": 0.65,
    "A": 0.1,
    "N": 0.66
  },
  "MAR0955": {
    "O": 0.65,
    "C": 0.85,
    "E": 0.33,
    "A": 0.85,
    "N": 0.31
  },
  "GRM0868": {
    "O": 0.28,
    "C": 0.38,
    "E": 0.25,
    "A": 0.07,
    "N": 0.4
  },
  "AAL0706": {
    "O": 0.68,
    "C": 0.1,
    "E": 0.45,
    "A": 0.07,
    "N": 0.31
  },
  "RVC0232": {
    "O": 0.6,
    "C": 0.25,
    "E": 0.93,
    "A": 0.7,
    "N": 0.31
  },
  "TCD0009": {
    "O": 0.85,
    "C": 0.45,
    "E": 0.85,
    "A": 0.7,
    "N": 0.26
  },
  "ASM0575": {
    "O": 0.8,
    "C": 0.38,
    "E": 0.28,
    "A": 0.88,
    "N": 0.46
  },
  "DAR0885": {
    "O": 0.82,
    "C": 0.82,
    "E": 0.85,
    "A": 0.78,
    "N": 0.31
  },
  "JLM0364": {
    "O": 0.62,
    "C": 0.3,
    "E": 0.12,
    "A": 0.38,
    "N": 0.66
  },
  "FOB0756": {
    "O": 0.8,
    "C": 0.78,
    "E": 0.6,
    "A": 0.25,
    "N": 0.37
  },
  "GCG0951": {
    "O": 0.58,
    "C": 0.58,
    "E": 0.38,
    "A": 0.23,
    "N": 0.86
  },
  "HWY0038": {
    "O": 0.93,
    "C": 0.73,
    "E": 0.75,
    "A": 0.3,
    "N": 0.29
  },
  "AAV0450": {
    "O": 0.85,
    "C": 0.35,
    "E": 0.65,
    "A": 0.78,
    "N": 0.54
  },
  "CJV0286": {
    "O": 0.2,
    "C": 0.1,
    "E": 0.17,
    "A": 0.07,
    "N": 0.34
  },
  "TDG0962": {
    "O": 0.8,
    "C": 0.75,
    "E": 0.65,
    "A": 0.4,
    "N": 0.2
  },
  "SVL0803": {
    "O": 0.42,
    "C": 0.62,
    "E": 0.25,
    "A": 0.65,
    "N": 0.51
  },
  "QOS0878": {
    "O": 0.2,
    "C": 0.05,
    "E": 0.25,
    "A": 0.15,
    "N": 0.43
  },
  "MDM0625": {
    "O": 0.2,
    "C": 0.8,
    "E": 0.65,
    "A": 0.42,
    "N": 0.29
  },
  "GMF0738": {
    "O": 0.5,
    "C": 0.75,
    "E": 0.88,
    "A": 0.25,
    "N": 0.11
  },
  "BER0314": {
    "O": 0.33,
    "C": 0.25,
    "E": 0.2,
    "A": 0.23,
    "N": 0.51
  },
  "AMR0400": {
    "O": 0.23,
    "C": 0.15,
    "E": 0.93,
    "A": 0.45,
    "N": 0.4
  },
  "YCE0983": {
    "O": 0.73,
    "C": 0.28,
    "E": 0.8,
    "A": 0.5,
    "N": 0.63
  },
  "BJW0619": {
    "O": 0.5,
    "C": 0.82,
    "E": 0.93,
    "A": 0.28,
    "N": 0.71
  },
  "DPS0262": {
    "O": 0.25,
    "C": 0.38,
    "E": 0.25,
    "A": 0.1,
    "N": 0.51
  },
  "TYB0779": {
    "O": 0.35,
    "C": 0.25,
    "E": 0.62,
    "A": 0.65,
    "N": 0.57
  },
  "MAS0025": {
    "O": 0.33,
    "C": 0.1,
    "E": 0.25,
    "A": 0.28,
    "N": 0.26
  },
  "KBL0260": {
    "O": 0.15,
    "C": 0.12,
    "E": 0.95,
    "A": 0.15,
    "N": 0.51
  },
  "GHL0460": {
    "O": 0.28,
    "C": 0.68,
    "E": 0.35,
    "A": 0.17,
    "N": 0.6
  },
  "FMG0527": {
    "O": 0.82,
    "C": 0.7,
    "E": 0.62,
    "A": 0.7,
    "N": 0.4
  },
  "HCL0651": {
    "O": 0.28,
    "C": 0.23,
    "E": 0.85,
    "A": 0.65,
    "N": 0.54
  },
  "SCP0130": {
    "O": 0.8,
    "C": 0.2,
    "E": 0.62,
    "A": 0.55,
    "N": 0.29
  },
  "CMW0783": {
    "O": 0.28,
    "C": 0.62,
    "E": 0.1,
    "A": 0.15,
    "N": 0.34
  },
  "RKF0164": {
    "O": 0.75,
    "C": 0.8,
    "E": 0.17,
    "A": 0.2,
    "N": 0.8
  },
  "DOL0332": {
    "O": 0.55,
    "C": 0.75,
    "E": 0.78,
    "A": 0.2,
    "N": 0.29
  },
  "RSC0089": {
    "O": 0.78,
    "C": 0.4,
    "E": 0.62,
    "A": 0.28,
    "N": 0.43
  },
  "CCM0136": {
    "O": 0.15,
    "C": 0.15,
    "E": 0.73,
    "A": 0.75,
    "N": 0.43
  },
  "NCH0179": {
    "O": 0.17,
    "C": 0.05,
    "E": 0.75,
    "A": 0.17,
    "N": 0.31
  },
  "NBH0256": {
    "O": 0.78,
    "C": 0.82,
    "E": 0.1,
    "A": 0.28,
    "N": 0.23
  },
  "ORG0339": {
    "O": 1.0,
    "C": 0.45,
    "E": 0.9,
    "A": 0.93,
    "N": 0.17
  },
  "FRR0832": {
    "O": 0.82,
    "C": 0.75,
    "E": 0.38,
    "A": 0.23,
    "N": 0.46
  },
  "MSD0939": {
    "O": 0.35,
    "C": 0.68,
    "E": 0.12,
    "A": 0.8,
    "N": 0.49
  },
  "OQH0183": {
    "O": 0.6,
    "C": 0.7,
    "E": 0.2,
    "A": 0.58,
    "N": 0.26
  },
  "BSH0445": {
    "O": 0.7,
    "C": 0.3,
    "E": 0.5,
    "A": 0.12,
    "N": 0.2
  },
  "KSP0357": {
    "O": 0.78,
    "C": 0.75,
    "E": 0.48,
    "A": 0.23,
    "N": 0.29
  },
  "NGO0690": {
    "O": 0.82,
    "C": 0.78,
    "E": 0.78,
    "A": 0.17,
    "N": 0.29
  },
  "VCC0396": {
    "O": 0.28,
    "C": 0.88,
    "E": 0.15,
    "A": 0.68,
    "N": 0.26
  },
  "WDD0366": {
    "O": 0.82,
    "C": 0.8,
    "E": 0.17,
    "A": 0.23,
    "N": 0.4
  },
  "KPP0452": {
    "O": 0.85,
    "C": 0.9,
    "E": 0.85,
    "A": 0.15,
    "N": 0.14
  },
  "RTO0313": {
    "O": 0.85,
    "C": 0.88,
    "E": 0.38,
    "A": 0.17,
    "N": 0.37
  },
  "ABM0845": {
    "O": 0.88,
    "C": 0.28,
    "E": 0.62,
    "A": 1.0,
    "N": 0.43
  },
  "VIA0063": {
    "O": 0.75,
    "C": 0.6,
    "E": 0.23,
    "A": 1.0,
    "N": 0.54
  },
  "BIH0745": {
    "O": 0.82,
    "C": 0.73,
    "E": 1.0,
    "A": 0.42,
    "N": 0.31
  },
  "CCW0031": {
    "O": 0.58,
    "C": 0.93,
    "E": 0.5,
    "A": 0.73,
    "N": 0.54
  },
  "IYB0918": {
    "O": 0.17,
    "C": 0.28,
    "E": 0.8,
    "A": 0.1,
    "N": 0.46
  },
  "ORM0669": {
    "O": 0.85,
    "C": 0.73,
    "E": 0.45,
    "A": 0.73,
    "N": 0.63
  },
  "MJB0588": {
    "O": 0.73,
    "C": 0.35,
    "E": 0.12,
    "A": 0.93,
    "N": 0.69
  },
  "ALB0892": {
    "O": 0.38,
    "C": 0.23,
    "E": 0.85,
    "A": 0.3,
    "N": 0.46
  },
  "LIM0674": {
    "O": 0.2,
    "C": 0.07,
    "E": 0.62,
    "A": 0.97,
    "N": 0.17
  },
  "LHN0151": {
    "O": 0.07,
    "C": 0.12,
    "E": 0.23,
    "A": 0.55,
    "N": 0.34
  },
  "WTR0563": {
    "O": 0.93,
    "C": 0.88,
    "E": 0.9,
    "A": 0.12,
    "N": 0.49
  },
  "MKS0204": {
    "O": 0.28,
    "C": 0.5,
    "E": 0.28,
    "A": 0.15,
    "N": 0.49
  },
  "AAW0353": {
    "O": 0.97,
    "C": 0.88,
    "E": 0.23,
    "A": 0.38,
    "N": 0.57
  },
  "WJD0576": {
    "O": 0.75,
    "C": 0.25,
    "E": 0.33,
    "A": 0.7,
    "N": 0.34
  },
  "ILH0958": {
    "O": 0.45,
    "C": 0.17,
    "E": 0.25,
    "A": 0.23,
    "N": 0.29
  },
  "TLK0993": {
    "O": 0.78,
    "C": 0.65,
    "E": 0.75,
    "A": 0.62,
    "N": 0.23
  },
  "WAB0143": {
    "O": 0.82,
    "C": 0.82,
    "E": 0.35,
    "A": 0.3,
    "N": 0.54
  },
  "RAG0275": {
    "O": 0.33,
    "C": 0.7,
    "E": 0.62,
    "A": 0.78,
    "N": 0.51
  },
  "LQC0479": {
    "O": 0.42,
    "C": 0.7,
    "E": 0.6,
    "A": 0.17,
    "N": 0.63
  },
  "KWC0004": {
    "O": 0.33,
    "C": 0.7,
    "E": 0.73,
    "A": 0.25,
    "N": 0.37
  },
  "CJK0200": {
    "O": 0.75,
    "C": 0.48,
    "E": 0.35,
    "A": 0.7,
    "N": 0.49
  },
  "FEB0306": {
    "O": 0.75,
    "C": 0.8,
    "E": 0.4,
    "A": 0.38,
    "N": 0.49
  },
  "IJM0776": {
    "O": 0.78,
    "C": 0.62,
    "E": 0.23,
    "A": 0.78,
    "N": 0.51
  },
  "NKH0807": {
    "O": 0.88,
    "C": 0.85,
    "E": 0.75,
    "A": 0.3,
    "N": 0.17
  },
  "JMC0925": {
    "O": 0.58,
    "C": 0.0,
    "E": 0.33,
    "A": 0.23,
    "N": 0.49
  },
  "SBH0537": {
    "O": 0.6,
    "C": 0.28,
    "E": 0.1,
    "A": 0.07,
    "N": 0.54
  },
  "JJB0700": {
    "O": 0.12,
    "C": 0.23,
    "E": 0.73,
    "A": 0.68,
    "N": 0.4
  },
  "AIS0405": {
    "O": 0.75,
    "C": 0.88,
    "E": 0.1,
    "A": 0.68,
    "N": 0.6
  },
  "HAH0760": {
    "O": 0.6,
    "C": 0.17,
    "E": 0.3,
    "A": 0.68,
    "N": 0.46
  },
  "AHD0848": {
    "O": 0.35,
    "C": 0.5,
    "E": 0.97,
    "A": 0.15,
    "N": 0.46
  },
  "LDM0587": {
    "O": 0.97,
    "C": 0.25,
    "E": 0.33,
    "A": 0.28,
    "N": 0.34
  },
  "AJN0607": {
    "O": 0.88,
    "C": 0.8,
    "E": 0.15,
    "A": 0.93,
    "N": 0.26
  },
  "BBS0039": {
    "O": 0.85,
    "C": 0.68,
    "E": 0.6,
    "A": 0.28,
    "N": 0.74
  },
  "EIS0041": {
    "O": 0.78,
    "C": 0.85,
    "E": 0.17,
    "A": 0.95,
    "N": 0.46
  },
  "MLG0475": {
    "O": 0.88,
    "C": 0.15,
    "E": 0.2,
    "A": 0.23,
    "N": 0.31
  },
  "HRD0635": {
    "O": 0.35,
    "C": 0.62,
    "E": 0.2,
    "A": 0.55,
    "N": 0.29
  },
  "EPW0434": {
    "O": 0.55,
    "C": 0.65,
    "E": 0.7,
    "A": 0.3,
    "N": 0.54
  },
  "JAM0382": {
    "O": 0.38,
    "C": 0.33,
    "E": 0.78,
    "A": 0.17,
    "N": 0.26
  },
  "NCK0295": {
    "O": 0.53,
    "C": 0.5,
    "E": 0.7,
    "A": 0.65,
    "N": 0.57
  },
  "LJT0817": {
    "O": 0.73,
    "C": 0.82,
    "E": 0.7,
    "A": 0.73,
    "N": 0.29
  },
  "CAM0102": {
    "O": 0.53,
    "C": 0.85,
    "E": 0.23,
    "A": 0.12,
    "N": 0.37
  },
  "SOG0411": {
    "O": 0.4,
    "C": 0.23,
    "E": 0.28,
    "A": 0.35,
    "N": 0.26
  },
  "KSH0569": {
    "O": 0.12,
    "C": 0.73,
    "E": 0.33,
    "A": 0.1,
    "N": 0.23
  },
  "BDI0533": {
    "O": 0.68,
    "C": 0.65,
    "E": 0.12,
    "A": 0.78,
    "N": 0.14
  },
  "PMJ0564": {
    "O": 0.5,
    "C": 0.28,
    "E": 0.75,
    "A": 0.1,
    "N": 0.71
  },
  "HGG0240": {
    "O": 0.25,
    "C": 0.4,
    "E": 0.35,
    "A": 0.65,
    "N": 0.49
  },
  "MGS0974": {
    "O": 0.17,
    "C": 0.73,
    "E": 0.73,
    "A": 0.75,
    "N": 0.37
  },
  "DHM0937": {
    "O": 0.82,
    "C": 0.3,
    "E": 0.28,
    "A": 0.12,
    "N": 0.29
  },
  "ENC0234": {
    "O": 0.28,
    "C": 0.33,
    "E": 0.55,
    "A": 0.23,
    "N": 0.26
  },
  "CEB0210": {
    "O": 0.8,
    "C": 0.35,
    "E": 0.85,
    "A": 0.33,
    "N": 0.57
  },
  "YJV0699": {
    "O": 0.17,
    "C": 0.38,
    "E": 0.5,
    "A": 0.07,
    "N": 0.49
  },
  "BMT0528": {
    "O": 0.58,
    "C": 0.38,
    "E": 0.73,
    "A": 0.38,
    "N": 0.46
  },
  "CJC0494": {
    "O": 0.75,
    "C": 0.73,
    "E": 0.73,
    "A": 0.8,
    "N": 0.8
  },
  "SOB0360": {
    "O": 0.8,
    "C": 0.3,
    "E": 0.75,
    "A": 0.15,
    "N": 0.51
  },
  "GCS0571": {
    "O": 0.3,
    "C": 0.2,
    "E": 0.15,
    "A": 0.33,
    "N": 0.51
  },
  "BJP0134": {
    "O": 0.8,
    "C": 0.17,
    "E": 0.85,
    "A": 0.28,
    "N": 0.71
  },
  "KBP0008": {
    "O": 0.33,
    "C": 0.2,
    "E": 0.75,
    "A": 0.03,
    "N": 0.57
  },
  "FLM0213": {
    "O": 0.25,
    "C": 0.78,
    "E": 0.9,
    "A": 0.12,
    "N": 0.29
  },
  "RRP0568": {
    "O": 0.82,
    "C": 1.0,
    "E": 0.7,
    "A": 0.2,
    "N": 0.54
  },
  "MCF0600": {
    "O": 0.73,
    "C": 0.97,
    "E": 0.07,
    "A": 0.4,
    "N": 0.37
  },
  "SAA0999": {
    "O": 0.25,
    "C": 0.17,
    "E": 0.6,
    "A": 0.03,
    "N": 0.63
  },
  "THR0873": {
    "O": 0.68,
    "C": 0.85,
    "E": 0.28,
    "A": 0.75,
    "N": 0.69
  },
  "KRM0541": {
    "O": 0.75,
    "C": 0.25,
    "E": 0.7,
    "A": 0.65,
    "N": 0.26
  },
  "KSP0966": {
    "O": 0.8,
    "C": 0.65,
    "E": 0.23,
    "A": 0.35,
    "N": 0.6
  },
  "LOF0311": {
    "O": 0.78,
    "C": 0.12,
    "E": 0.65,
    "A": 0.0,
    "N": 0.51
  },
  "MBR0724": {
    "O": 0.58,
    "C": 0.85,
    "E": 0.2,
    "A": 0.62,
    "N": 0.49
  },
  "FSC0601": {
    "O": 0.68,
    "C": 0.5,
    "E": 0.68,
    "A": 0.12,
    "N": 0.46
  },
  "MLP0668": {
    "O": 0.75,
    "C": 0.17,
    "E": 0.15,
    "A": 0.82,
    "N": 0.54
  },
  "CUD0795": {
    "O": 0.05,
    "C": 0.75,
    "E": 0.5,
    "A": 0.85,
    "N": 0.29
  },
  "AKR0057": {
    "O": 1.0,
    "C": 0.78,
    "E": 0.25,
    "A": 0.2,
    "N": 0.46
  },
  "GZC0735": {
    "O": 0.85,
    "C": 0.15,
    "E": 0.12,
    "A": 0.42,
    "N": 0.31
  },
  "HLH0512": {
    "O": 0.12,
    "C": 0.8,
    "E": 0.65,
    "A": 0.3,
    "N": 0.51
  },
  "NJB0243": {
    "O": 0.33,
    "C": 0.62,
    "E": 0.68,
    "A": 0.35,
    "N": 0.57
  },
  "GCS0518": {
    "O": 0.78,
    "C": 0.65,
    "E": 0.33,
    "A": 0.7,
    "N": 0.2
  },
  "NMC0486": {
    "O": 0.8,
    "C": 0.0,
    "E": 0.33,
    "A": 0.28,
    "N": 0.37
  },
  "KMB0922": {
    "O": 0.82,
    "C": 0.82,
    "E": 0.17,
    "A": 0.35,
    "N": 0.37
  },
  "CFM0767": {
    "O": 0.9,
    "C": 0.33,
    "E": 0.3,
    "A": 0.62,
    "N": 0.43
  },
  "HAD0246": {
    "O": 0.85,
    "C": 0.73,
    "E": 0.55,
    "A": 0.88,
    "N": 0.69
  },
  "ANP0555": {
    "O": 0.07,
    "C": 0.75,
    "E": 0.8,
    "A": 0.33,
    "N": 0.4
  },
  "LBF0214": {
    "O": 0.2,
    "C": 0.85,
    "E": 0.2,
    "A": 0.7,
    "N": 0.4
  },
  "DJB0159": {
    "O": 0.25,
    "C": 0.68,
    "E": 0.42,
    "A": 0.7,
    "N": 0.66
  },
  "BWP0202": {
    "O": 0.25,
    "C": 0.65,
    "E": 0.12,
    "A": 0.38,
    "N": 0.4
  },
  "FFC0891": {
    "O": 0.7,
    "C": 0.0,
    "E": 0.73,
    "A": 1.0,
    "N": 0.71
  },
  "AJR0932": {
    "O": 0.9,
    "C": 0.5,
    "E": 0.62,
    "A": 0.05,
    "N": 0.43
  },
  "BDV0168": {
    "O": 0.88,
    "C": 0.53,
    "E": 0.23,
    "A": 0.28,
    "N": 0.49
  },
  "CQH0730": {
    "O": 0.28,
    "C": 0.2,
    "E": 0.68,
    "A": 0.97,
    "N": 0.37
  },
  "JCR0289": {
    "O": 0.55,
    "C": 0.82,
    "E": 0.58,
    "A": 0.58,
    "N": 0.43
  },
  "AES0827": {
    "O": 0.73,
    "C": 0.75,
    "E": 0.6,
    "A": 0.7,
    "N": 0.26
  },
  "SLP0762": {
    "O": 0.4,
    "C": 0.07,
    "E": 0.75,
    "A": 0.2,
    "N": 0.34
  },
  "CLD0894": {
    "O": 0.23,
    "C": 0.28,
    "E": 1.0,
    "A": 0.15,
    "N": 0.63
  },
  "LCD0622": {
    "O": 0.5,
    "C": 0.4,
    "E": 0.07,
    "A": 0.1,
    "N": 0.34
  },
  "CMB0912": {
    "O": 0.9,
    "C": 0.82,
    "E": 0.15,
    "A": 0.3,
    "N": 0.49
  },
  "ZKS0899": {
    "O": 0.93,
    "C": 0.25,
    "E": 0.8,
    "A": 0.82,
    "N": 0.46
  },
  "JCV0245": {
    "O": 0.75,
    "C": 0.85,
    "E": 0.3,
    "A": 0.25,
    "N": 0.37
  },
  "AMH0794": {
    "O": 0.82,
    "C": 0.8,
    "E": 0.58,
    "A": 0.75,
    "N": 0.49
  },
  "FKB0163": {
    "O": 0.73,
    "C": 0.62,
    "E": 0.38,
    "A": 0.73,
    "N": 0.23
  },
  "AKC0924": {
    "O": 0.75,
    "C": 0.85,
    "E": 0.62,
    "A": 0.68,
    "N": 0.37
  },
  "ILR0304": {
    "O": 0.25,
    "C": 0.3,
    "E": 0.2,
    "A": 0.9,
    "N": 0.46
  },
  "AJF0370": {
    "O": 0.68,
    "C": 0.58,
    "E": 0.03,
    "A": 0.12,
    "N": 0.63
  },
  "OKC0107": {
    "O": 0.55,
    "C": 0.75,
    "E": 0.15,
    "A": 0.93,
    "N": 0.6
  },
  "OCS0865": {
    "O": 0.48,
    "C": 0.35,
    "E": 0.82,
    "A": 0.62,
    "N": 0.51
  },
  "UJC0737": {
    "O": 0.15,
    "C": 0.05,
    "E": 0.05,
    "A": 0.7,
    "N": 0.31
  },
  "MBW0809": {
    "O": 0.82,
    "C": 0.88,
    "E": 0.85,
    "A": 0.2,
    "N": 0.14
  },
  "MCF0327": {
    "O": 0.73,
    "C": 0.78,
    "E": 0.35,
    "A": 0.85,
    "N": 0.31
  },
  "SGS0268": {
    "O": 0.93,
    "C": 0.88,
    "E": 0.5,
    "A": 0.23,
    "N": 0.23
  },
  "BNG0237": {
    "O": 0.73,
    "C": 0.65,
    "E": 0.65,
    "A": 0.93,
    "N": 0.37
  },
  "OSH0655": {
    "O": 0.15,
    "C": 0.28,
    "E": 0.8,
    "A": 0.73,
    "N": 0.4
  },
  "CSB0080": {
    "O": 0.62,
    "C": 0.23,
    "E": 0.73,
    "A": 0.6,
    "N": 0.63
  },
  "ERH0449": {
    "O": 0.85,
    "C": 0.12,
    "E": 0.62,
    "A": 0.17,
    "N": 0.31
  },
  "EGK0893": {
    "O": 0.28,
    "C": 0.5,
    "E": 0.03,
    "A": 0.93,
    "N": 0.37
  },
  "MMB0488": {
    "O": 0.28,
    "C": 0.2,
    "E": 0.15,
    "A": 0.35,
    "N": 0.37
  },
  "AAM0658": {
    "O": 0.82,
    "C": 0.62,
    "E": 0.68,
    "A": 0.65,
    "N": 0.23
  },
  "ESA0642": {
    "O": 0.55,
    "C": 0.1,
    "E": 0.85,
    "A": 0.5,
    "N": 0.51
  },
  "CRK0916": {
    "O": 0.55,
    "C": 0.9,
    "E": 0.4,
    "A": 0.23,
    "N": 0.51
  },
  "BBH0810": {
    "O": 0.75,
    "C": 0.38,
    "E": 0.0,
    "A": 0.28,
    "N": 0.51
  },
  "JRF0835": {
    "O": 0.85,
    "C": 0.58,
    "E": 0.2,
    "A": 0.68,
    "N": 0.11
  },
  "SJC0333": {
    "O": 0.3,
    "C": 0.73,
    "E": 0.53,
    "A": 0.65,
    "N": 0.43
  },
  "HCS0003": {
    "O": 0.62,
    "C": 0.45,
    "E": 0.1,
    "A": 0.12,
    "N": 0.46
  },
  "EMB0531": {
    "O": 0.53,
    "C": 0.78,
    "E": 0.53,
    "A": 0.65,
    "N": 0.63
  },
  "JIM0095": {
    "O": 0.0,
    "C": 0.2,
    "E": 0.28,
    "A": 0.12,
    "N": 0.6
  },
  "KJS0618": {
    "O": 0.23,
    "C": 0.12,
    "E": 0.25,
    "A": 0.0,
    "N": 0.66
  },
  "EBC0390": {
    "O": 0.75,
    "C": 0.75,
    "E": 0.75,
    "A": 0.3,
    "N": 0.54
  },
  "WGS0516": {
    "O": 0.03,
    "C": 0.25,
    "E": 0.73,
    "A": 0.25,
    "N": 0.43
  },
  "NGF0157": {
    "O": 0.88,
    "C": 0.7,
    "E": 0.3,
    "A": 0.9,
    "N": 0.51
  },
  "KAT0489": {
    "O": 0.3,
    "C": 0.78,
    "E": 0.65,
    "A": 0.33,
    "N": 0.34
  },
  "CCH0685": {
    "O": 0.93,
    "C": 0.35,
    "E": 0.8,
    "A": 0.6,
    "N": 0.43
  },
  "DMM0623": {
    "O": 0.65,
    "C": 0.42,
    "E": 0.28,
    "A": 0.73,
    "N": 0.46
  },
  "SAH0599": {
    "O": 0.07,
    "C": 0.3,
    "E": 0.85,
    "A": 0.2,
    "N": 0.23
  },
  "CPG0322": {
    "O": 0.17,
    "C": 0.07,
    "E": 0.23,
    "A": 0.35,
    "N": 0.63
  },
  "OBH0499": {
    "O": 0.62,
    "C": 0.2,
    "E": 0.78,
    "A": 0.15,
    "N": 0.57
  },
  "SNS0129": {
    "O": 0.4,
    "C": 0.0,
    "E": 0.82,
    "A": 0.62,
    "N": 0.46
  },
  "PKB0429": {
    "O": 0.6,
    "C": 0.8,
    "E": 0.82,
    "A": 0.75,
    "N": 0.23
  },
  "NAH0503": {
    "O": 0.58,
    "C": 0.17,
    "E": 0.33,
    "A": 0.62,
    "N": 0.69
  },
  "FRB0023": {
    "O": 0.88,
    "C": 0.1,
    "E": 0.05,
    "A": 0.1,
    "N": 0.0
  },
  "AHG0634": {
    "O": 0.53,
    "C": 0.65,
    "E": 0.8,
    "A": 0.78,
    "N": 0.37
  },
  "CWB0065": {
    "O": 1.0,
    "C": 0.58,
    "E": 0.1,
    "A": 0.25,
    "N": 0.26
  },
  "ATP0662": {
    "O": 0.17,
    "C": 0.15,
    "E": 0.78,
    "A": 0.25,
    "N": 0.71
  },
  "DPM0423": {
    "O": 0.68,
    "C": 0.7,
    "E": 0.7,
    "A": 0.12,
    "N": 0.37
  },
  "WKF0012": {
    "O": 0.68,
    "C": 0.85,
    "E": 0.25,
    "A": 0.88,
    "N": 0.26
  },
  "JMB0308": {
    "O": 0.78,
    "C": 0.85,
    "E": 0.6,
    "A": 0.1,
    "N": 0.51
  },
  "AKF0709": {
    "O": 0.8,
    "C": 0.53,
    "E": 0.48,
    "A": 0.3,
    "N": 0.51
  },
  "JMH0543": {
    "O": 0.85,
    "C": 0.38,
    "E": 0.68,
    "A": 0.07,
    "N": 0.57
  },
  "CJF0802": {
    "O": 0.65,
    "C": 0.73,
    "E": 0.7,
    "A": 0.82,
    "N": 0.2
  },
  "IRM0931": {
    "O": 0.85,
    "C": 0.9,
    "E": 0.58,
    "A": 0.62,
    "N": 0.46
  },
  "FQA0854": {
    "O": 0.78,
    "C": 0.7,
    "E": 0.5,
    "A": 0.6,
    "N": 0.34
  },
  "CYA0506": {
    "O": 0.15,
    "C": 0.17,
    "E": 0.85,
    "A": 0.1,
    "N": 0.49
  },
  "GRC0145": {
    "O": 0.5,
    "C": 0.82,
    "E": 0.35,
    "A": 0.9,
    "N": 0.37
  },
  "BLS0678": {
    "O": 0.62,
    "C": 0.17,
    "E": 0.82,
    "A": 0.45,
    "N": 0.49
  },
  "HJB0742": {
    "O": 0.78,
    "C": 0.75,
    "E": 0.15,
    "A": 0.28,
    "N": 0.46
  },
  "KKS0119": {
    "O": 0.12,
    "C": 0.45,
    "E": 0.73,
    "A": 0.58,
    "N": 0.37
  },
  "RAB0589": {
    "O": 0.65,
    "C": 0.62,
    "E": 0.4,
    "A": 0.1,
    "N": 0.49
  },
  "DBB0384": {
    "O": 0.75,
    "C": 0.78,
    "E": 0.45,
    "A": 0.68,
    "N": 0.37
  },
  "TRK0914": {
    "O": 0.75,
    "C": 0.23,
    "E": 0.1,
    "A": 0.58,
    "N": 0.46
  },
  "BSA0431": {
    "O": 1.0,
    "C": 0.78,
    "E": 0.23,
    "A": 0.75,
    "N": 0.43
  },
  "RHL0992": {
    "O": 0.65,
    "C": 0.0,
    "E": 0.73,
    "A": 0.68,
    "N": 0.63
  },
  "CIM0926": {
    "O": 0.53,
    "C": 0.38,
    "E": 0.78,
    "A": 0.17,
    "N": 0.49
  },
  "CFG0959": {
    "O": 0.8,
    "C": 0.28,
    "E": 0.35,
    "A": 0.17,
    "N": 0.17
  },
  "VMJ0147": {
    "O": 0.33,
    "C": 0.45,
    "E": 0.68,
    "A": 0.3,
    "N": 0.29
  },
  "SAT0194": {
    "O": 0.1,
    "C": 0.23,
    "E": 0.65,
    "A": 0.33,
    "N": 0.6
  },
  "HBO0413": {
    "O": 0.78,
    "C": 0.62,
    "E": 0.2,
    "A": 0.12,
    "N": 0.11
  },
  "DZC0228": {
    "O": 0.68,
    "C": 0.68,
    "E": 0.6,
    "A": 0.28,
    "N": 0.69
  },
  "TEB0251": {
    "O": 0.85,
    "C": 1.0,
    "E": 0.3,
    "A": 0.07,
    "N": 0.63
  },
  "MNR0829": {
    "O": 0.78,
    "C": 0.58,
    "E": 0.75,
    "A": 0.12,
    "N": 0.26
  },
  "DOP0562": {
    "O": 0.8,
    "C": 0.15,
    "E": 0.68,
    "A": 0.73,
    "N": 0.49
  },
  "UAD0771": {
    "O": 0.9,
    "C": 0.6,
    "E": 0.12,
    "A": 0.5,
    "N": 0.49
  },
  "ALD0544": {
    "O": 0.15,
    "C": 0.2,
    "E": 0.2,
    "A": 0.07,
    "N": 0.51
  },
  "LCB0664": {
    "O": 0.15,
    "C": 0.23,
    "E": 0.65,
    "A": 0.35,
    "N": 0.51
  },
  "HCL0113": {
    "O": 0.82,
    "C": 0.3,
    "E": 0.75,
    "A": 0.73,
    "N": 0.57
  },
  "TSB0437": {
    "O": 0.4,
    "C": 0.33,
    "E": 0.15,
    "A": 0.5,
    "N": 0.34
  },
  "EZH0736": {
    "O": 0.85,
    "C": 0.78,
    "E": 0.68,
    "A": 0.23,
    "N": 0.49
  },
  "JCG0316": {
    "O": 0.93,
    "C": 0.65,
    "E": 0.55,
    "A": 0.38,
    "N": 0.54
  },
  "MSG0839": {
    "O": 0.8,
    "C": 0.9,
    "E": 0.23,
    "A": 0.73,
    "N": 0.43
  },
  "LJJ0905": {
    "O": 0.82,
    "C": 0.65,
    "E": 0.05,
    "A": 0.3,
    "N": 0.46
  },
  "HCM0267": {
    "O": 0.65,
    "C": 0.88,
    "E": 0.73,
    "A": 0.25,
    "N": 0.51
  },
  "MTB0620": {
    "O": 0.7,
    "C": 0.85,
    "E": 0.78,
    "A": 1.0,
    "N": 0.4
  },
  "CCH0182": {
    "O": 0.8,
    "C": 0.85,
    "E": 0.93,
    "A": 0.33,
    "N": 0.43
  },
  "CAM0681": {
    "O": 0.78,
    "C": 0.82,
    "E": 0.88,
    "A": 0.0,
    "N": 0.4
  },
  "LBH0942": {
    "O": 0.75,
    "C": 0.8,
    "E": 0.33,
    "A": 0.5,
    "N": 0.43
  },
  "CAB0388": {
    "O": 0.68,
    "C": 0.58,
    "E": 0.33,
    "A": 0.75,
    "N": 0.63
  },
  "WGR0833": {
    "O": 0.7,
    "C": 0.9,
    "E": 0.35,
    "A": 0.7,
    "N": 0.8
  },
  "MTT0901": {
    "O": 0.78,
    "C": 0.6,
    "E": 0.5,
    "A": 0.75,
    "N": 0.46
  },
  "GQF0659": {
    "O": 0.75,
    "C": 0.15,
    "E": 0.5,
    "A": 0.48,
    "N": 0.4
  },
  "CSP0197": {
    "O": 0.68,
    "C": 0.85,
    "E": 0.17,
    "A": 0.07,
    "N": 0.34
  },
  "OMM0944": {
    "O": 0.17,
    "C": 0.1,
    "E": 0.42,
    "A": 0.28,
    "N": 0.43
  },
  "IMP0530": {
    "O": 0.75,
    "C": 0.17,
    "E": 0.8,
    "A": 1.0,
    "N": 0.51
  },
  "ORB0473": {
    "O": 0.7,
    "C": 0.85,
    "E": 0.9,
    "A": 0.7,
    "N": 0.69
  },
  "JML0909": {
    "O": 0.35,
    "C": 0.55,
    "E": 0.73,
    "A": 0.75,
    "N": 0.2
  },
  "NDM0417": {
    "O": 0.85,
    "C": 0.65,
    "E": 1.0,
    "A": 0.05,
    "N": 0.57
  },
  "FRL0511": {
    "O": 0.25,
    "C": 0.5,
    "E": 0.93,
    "A": 0.25,
    "N": 0.46
  },
  "LAP0338": {
    "O": 0.8,
    "C": 0.33,
    "E": 0.58,
    "A": 0.88,
    "N": 0.49
  },
  "HCV0478": {
    "O": 0.9,
    "C": 0.65,
    "E": 0.2,
    "A": 0.05,
    "N": 0.29
  },
  "KJA0152": {
    "O": 0.15,
    "C": 0.15,
    "E": 0.73,
    "A": 0.7,
    "N": 0.57
  },
  "ECF0828": {
    "O": 0.75,
    "C": 0.97,
    "E": 0.73,
    "A": 0.75,
    "N": 0.6
  },
  "BVN0514": {
    "O": 0.65,
    "C": 0.33,
    "E": 0.5,
    "A": 0.33,
    "N": 0.23
  },
  "BSS0463": {
    "O": 0.55,
    "C": 0.75,
    "E": 0.75,
    "A": 0.7,
    "N": 0.4
  },
  "JJM0203": {
    "O": 0.68,
    "C": 0.65,
    "E": 0.2,
    "A": 0.5,
    "N": 0.4
  },
  "AIM0627": {
    "O": 0.65,
    "C": 0.73,
    "E": 0.15,
    "A": 0.78,
    "N": 0.26
  },
  "RAH0440": {
    "O": 0.2,
    "C": 0.12,
    "E": 0.82,
    "A": 0.15,
    "N": 0.29
  },
  "XHG0902": {
    "O": 0.85,
    "C": 0.62,
    "E": 0.33,
    "A": 0.93,
    "N": 0.0
  },
  "TDJ0998": {
    "O": 0.6,
    "C": 0.75,
    "E": 0.0,
    "A": 0.8,
    "N": 0.63
  },
  "JPA0667": {
    "O": 0.97,
    "C": 0.8,
    "E": 0.6,
    "A": 0.62,
    "N": 0.37
  },
  "EHR0096": {
    "O": 0.3,
    "C": 0.07,
    "E": 0.25,
    "A": 0.95,
    "N": 0.49
  },
  "SJW0451": {
    "O": 0.82,
    "C": 0.5,
    "E": 0.15,
    "A": 1.0,
    "N": 0.4
  },
  "CNB0900": {
    "O": 0.6,
    "C": 0.82,
    "E": 0.7,
    "A": 0.15,
    "N": 0.37
  },
  "EAH0466": {
    "O": 0.78,
    "C": 0.7,
    "E": 0.48,
    "A": 0.7,
    "N": 0.31
  },
  "CTA0020": {
    "O": 0.65,
    "C": 1.0,
    "E": 0.03,
    "A": 0.3,
    "N": 0.57
  },
  "SRS0231": {
    "O": 0.17,
    "C": 0.85,
    "E": 0.65,
    "A": 0.55,
    "N": 0.34
  },
  "HWH0646": {
    "O": 0.17,
    "C": 0.35,
    "E": 0.35,
    "A": 0.28,
    "N": 0.4
  },
  "HKB0418": {
    "O": 1.0,
    "C": 0.2,
    "E": 0.07,
    "A": 0.4,
    "N": 0.37
  },
  "CCM0855": {
    "O": 0.53,
    "C": 0.35,
    "E": 0.23,
    "A": 0.65,
    "N": 0.43
  },
  "SED0886": {
    "O": 0.3,
    "C": 0.2,
    "E": 0.2,
    "A": 0.62,
    "N": 0.4
  },
  "LBC0356": {
    "O": 0.75,
    "C": 0.5,
    "E": 0.75,
    "A": 0.28,
    "N": 0.77
  },
  "CKH0144": {
    "O": 0.6,
    "C": 0.3,
    "E": 0.3,
    "A": 0.62,
    "N": 0.46
  },
  "MBG0438": {
    "O": 0.7,
    "C": 0.17,
    "E": 0.68,
    "A": 0.15,
    "N": 0.43
  },
  "MVF0594": {
    "O": 0.62,
    "C": 0.7,
    "E": 0.58,
    "A": 0.85,
    "N": 0.63
  },
  "ATF0274": {
    "O": 0.25,
    "C": 0.88,
    "E": 0.95,
    "A": 0.42,
    "N": 0.4
  },
  "KTG0091": {
    "O": 0.9,
    "C": 0.78,
    "E": 0.15,
    "A": 0.12,
    "N": 0.43
  },
  "ACC0042": {
    "O": 0.33,
    "C": 0.23,
    "E": 0.68,
    "A": 0.25,
    "N": 0.49
  },
  "AKW0167": {
    "O": 0.7,
    "C": 0.7,
    "E": 0.25,
    "A": 0.1,
    "N": 0.6
  },
  "KPR0497": {
    "O": 1.0,
    "C": 0.82,
    "E": 0.82,
    "A": 0.25,
    "N": 0.43
  },
  "ABN0239": {
    "O": 0.28,
    "C": 0.68,
    "E": 0.25,
    "A": 0.73,
    "N": 0.31
  },
  "CKB0482": {
    "O": 0.65,
    "C": 0.95,
    "E": 0.68,
    "A": 0.9,
    "N": 0.31
  },
  "AMH0464": {
    "O": 0.88,
    "C": 0.15,
    "E": 0.8,
    "A": 0.68,
    "N": 0.2
  },
  "QCH0110": {
    "O": 0.6,
    "C": 0.62,
    "E": 0.17,
    "A": 0.68,
    "N": 0.37
  },
  "SGG0787": {
    "O": 0.1,
    "C": 0.42,
    "E": 0.0,
    "A": 0.25,
    "N": 0.49
  },
  "SIJ0661": {
    "O": 0.75,
    "C": 0.17,
    "E": 0.1,
    "A": 0.12,
    "N": 0.2
  },
  "BTW0005": {
    "O": 0.58,
    "C": 0.73,
    "E": 0.2,
    "A": 0.2,
    "N": 0.37
  },
  "RLB0719": {
    "O": 0.1,
    "C": 0.2,
    "E": 0.12,
    "A": 0.75,
    "N": 0.6
  },
  "WDO0870": {
    "O": 0.33,
    "C": 0.28,
    "E": 0.1,
    "A": 0.07,
    "N": 0.31
  },
  "KCB0815": {
    "O": 0.15,
    "C": 0.75,
    "E": 0.2,
    "A": 0.65,
    "N": 0.49
  },
  "VCY0751": {
    "O": 0.68,
    "C": 0.35,
    "E": 0.73,
    "A": 0.23,
    "N": 0.31
  },
  "BAJ0654": {
    "O": 0.65,
    "C": 0.0,
    "E": 0.93,
    "A": 0.0,
    "N": 0.77
  },
  "MKL0941": {
    "O": 0.15,
    "C": 0.4,
    "E": 0.25,
    "A": 0.7,
    "N": 0.46
  },
  "EGD0409": {
    "O": 0.73,
    "C": 0.75,
    "E": 0.3,
    "A": 0.62,
    "N": 0.54
  },
  "DBS0235": {
    "O": 0.5,
    "C": 0.7,
    "E": 0.2,
    "A": 0.68,
    "N": 0.54
  },
  "JJH0613": {
    "O": 1.0,
    "C": 0.5,
    "E": 0.35,
    "A": 0.1,
    "N": 0.34
  },
  "UFK0208": {
    "O": 0.2,
    "C": 0.6,
    "E": 0.3,
    "A": 0.33,
    "N": 0.46
  },
  "BLB0114": {
    "O": 0.7,
    "C": 0.95,
    "E": 0.78,
    "A": 0.12,
    "N": 0.23
  },
  "CKD0680": {
    "O": 0.2,
    "C": 1.0,
    "E": 0.35,
    "A": 0.2,
    "N": 0.4
  },
  "MKG0711": {
    "O": 0.17,
    "C": 0.4,
    "E": 0.82,
    "A": 0.55,
    "N": 0.69
  },
  "EDA0684": {
    "O": 0.7,
    "C": 0.8,
    "E": 0.75,
    "A": 0.73,
    "N": 0.54
  },
  "IIL0513": {
    "O": 0.68,
    "C": 0.07,
    "E": 0.4,
    "A": 0.7,
    "N": 0.57
  },
  "TSM0363": {
    "O": 0.6,
    "C": 0.23,
    "E": 0.25,
    "A": 0.73,
    "N": 0.54
  },
  "PBP0002": {
    "O": 0.97,
    "C": 0.62,
    "E": 0.33,
    "A": 0.0,
    "N": 0.37
  },
  "LHB0606": {
    "O": 0.68,
    "C": 0.7,
    "E": 0.12,
    "A": 0.42,
    "N": 0.37
  },
  "GTD0898": {
    "O": 0.33,
    "C": 0.33,
    "E": 0.73,
    "A": 0.12,
    "N": 0.43
  },
  "CJH0702": {
    "O": 0.9,
    "C": 0.35,
    "E": 0.5,
    "A": 0.38,
    "N": 0.66
  },
  "DMK0257": {
    "O": 0.58,
    "C": 0.25,
    "E": 0.4,
    "A": 0.4,
    "N": 0.46
  },
  "WIQ0567": {
    "O": 0.38,
    "C": 0.78,
    "E": 0.0,
    "A": 0.93,
    "N": 0.71
  },
  "PTH0830": {
    "O": 0.82,
    "C": 0.85,
    "E": 0.8,
    "A": 0.82,
    "N": 0.57
  },
  "NCO0666": {
    "O": 0.75,
    "C": 0.88,
    "E": 0.0,
    "A": 0.05,
    "N": 0.49
  },
  "MHG0733": {
    "O": 0.82,
    "C": 0.5,
    "E": 0.35,
    "A": 0.8,
    "N": 0.43
  },
  "RAW0915": {
    "O": 0.82,
    "C": 1.0,
    "E": 0.28,
    "A": 0.82,
    "N": 0.29
  },
  "HAM0985": {
    "O": 0.25,
    "C": 0.17,
    "E": 0.48,
    "A": 0.15,
    "N": 0.17
  },
  "SAB0781": {
    "O": 0.65,
    "C": 0.62,
    "E": 0.35,
    "A": 0.5,
    "N": 0.4
  },
  "IBM0671": {
    "O": 1.0,
    "C": 0.9,
    "E": 0.7,
    "A": 0.62,
    "N": 0.49
  },
  "YDN0198": {
    "O": 0.88,
    "C": 1.0,
    "E": 0.78,
    "A": 0.03,
    "N": 0.29
  },
  "GAF0060": {
    "O": 0.78,
    "C": 0.15,
    "E": 0.73,
    "A": 0.38,
    "N": 0.23
  },
  "AMM0014": {
    "O": 0.95,
    "C": 0.7,
    "E": 0.12,
    "A": 0.85,
    "N": 0.63
  },
  "AMV0036": {
    "O": 0.82,
    "C": 0.65,
    "E": 0.8,
    "A": 0.68,
    "N": 0.34
  },
  "MOP0763": {
    "O": 0.82,
    "C": 0.78,
    "E": 0.3,
    "A": 0.25,
    "N": 0.54
  },
  "CBG0490": {
    "O": 1.0,
    "C": 0.53,
    "E": 0.62,
    "A": 0.0,
    "N": 0.43
  },
  "CNE0352": {
    "O": 0.73,
    "C": 0.3,
    "E": 0.85,
    "A": 0.12,
    "N": 0.46
  },
  "GQP0743": {
    "O": 0.93,
    "C": 0.73,
    "E": 0.23,
    "A": 0.73,
    "N": 0.31
  },
  "PTH0552": {
    "O": 0.25,
    "C": 0.07,
    "E": 0.55,
    "A": 0.25,
    "N": 0.4
  },
  "GLR0975": {
    "O": 0.58,
    "C": 0.85,
    "E": 0.4,
    "A": 0.35,
    "N": 0.29
  },
  "GTD0219": {
    "O": 0.75,
    "C": 0.75,
    "E": 0.23,
    "A": 0.5,
    "N": 0.54
  },
  "BKW0374": {
    "O": 0.78,
    "C": 0.7,
    "E": 0.17,
    "A": 0.9,
    "N": 0.37
  },
  "CAH0936": {
    "O": 0.75,
    "C": 0.3,
    "E": 0.73,
    "A": 1.0,
    "N": 0.29
  },
  "AIP0982": {
    "O": 0.82,
    "C": 0.25,
    "E": 0.82,
    "A": 0.78,
    "N": 0.54
  },
  "KRV0372": {
    "O": 0.75,
    "C": 0.73,
    "E": 0.38,
    "A": 0.62,
    "N": 0.51
  },
  "IAT0263": {
    "O": 0.45,
    "C": 0.33,
    "E": 0.5,
    "A": 0.5,
    "N": 0.37
  },
  "JBD0616": {
    "O": 0.75,
    "C": 0.28,
    "E": 0.38,
    "A": 0.68,
    "N": 0.37
  },
  "RUM0880": {
    "O": 0.75,
    "C": 0.68,
    "E": 0.17,
    "A": 0.7,
    "N": 0.34
  },
  "DGM0754": {
    "O": 0.8,
    "C": 0.2,
    "E": 0.8,
    "A": 0.35,
    "N": 0.29
  },
  "SMY0792": {
    "O": 0.82,
    "C": 0.68,
    "E": 0.73,
    "A": 0.8,
    "N": 0.31
  },
  "HOB0994": {
    "O": 0.7,
    "C": 0.73,
    "E": 0.12,
    "A": 0.82,
    "N": 0.54
  },
  "DGN0480": {
    "O": 0.28,
    "C": 0.38,
    "E": 0.85,
    "A": 0.25,
    "N": 0.49
  },
  "KJJ0293": {
    "O": 0.78,
    "C": 0.8,
    "E": 0.33,
    "A": 0.73,
    "N": 0.54
  },
  "JXH0493": {
    "O": 0.65,
    "C": 0.55,
    "E": 0.33,
    "A": 0.12,
    "N": 0.49
  },
  "PGH0184": {
    "O": 0.5,
    "C": 0.62,
    "E": 0.58,
    "A": 0.3,
    "N": 0.31
  },
  "JPW0741": {
    "O": 0.75,
    "C": 0.7,
    "E": 0.85,
    "A": 0.5,
    "N": 0.54
  },
  "NMG0766": {
    "O": 0.15,
    "C": 0.33,
    "E": 0.8,
    "A": 0.75,
    "N": 0.49
  },
  "HMW0713": {
    "O": 0.7,
    "C": 0.35,
    "E": 0.75,
    "A": 0.65,
    "N": 0.4
  },
  "MAH0864": {
    "O": 0.5,
    "C": 0.9,
    "E": 0.38,
    "A": 0.25,
    "N": 0.31
  },
  "QNF0205": {
    "O": 0.62,
    "C": 0.78,
    "E": 0.3,
    "A": 0.28,
    "N": 0.43
  },
  "KKW0879": {
    "O": 0.65,
    "C": 0.8,
    "E": 0.28,
    "A": 0.53,
    "N": 0.37
  },
  "TEM0093": {
    "O": 0.45,
    "C": 0.35,
    "E": 0.88,
    "A": 0.1,
    "N": 0.46
  },
  "RVF0201": {
    "O": 0.65,
    "C": 0.55,
    "E": 0.7,
    "A": 0.48,
    "N": 0.4
  },
  "TMA0069": {
    "O": 0.58,
    "C": 0.7,
    "E": 0.8,
    "A": 0.1,
    "N": 0.54
  },
  "VFM0814": {
    "O": 0.9,
    "C": 0.88,
    "E": 0.85,
    "A": 0.23,
    "N": 0.4
  },
  "SBN0866": {
    "O": 0.78,
    "C": 0.6,
    "E": 0.78,
    "A": 0.35,
    "N": 0.23
  },
  "ZJE0857": {
    "O": 0.62,
    "C": 0.6,
    "E": 0.65,
    "A": 0.7,
    "N": 0.49
  },
  "HPM0986": {
    "O": 0.78,
    "C": 0.65,
    "E": 0.7,
    "A": 0.33,
    "N": 0.29
  },
  "CJP0952": {
    "O": 0.88,
    "C": 0.2,
    "E": 0.38,
    "A": 0.2,
    "N": 0.37
  },
  "DRR0162": {
    "O": 0.88,
    "C": 0.65,
    "E": 0.25,
    "A": 0.65,
    "N": 0.43
  },
  "ESR0693": {
    "O": 0.62,
    "C": 0.33,
    "E": 0.38,
    "A": 0.28,
    "N": 0.49
  },
  "CWR0502": {
    "O": 0.78,
    "C": 0.97,
    "E": 0.38,
    "A": 0.88,
    "N": 0.37
  },
  "SLB0049": {
    "O": 0.1,
    "C": 0.42,
    "E": 0.15,
    "A": 0.3,
    "N": 0.17
  },
  "IDO0176": {
    "O": 0.6,
    "C": 0.73,
    "E": 0.75,
    "A": 0.35,
    "N": 0.34
  },
  "AGB0186": {
    "O": 0.2,
    "C": 0.0,
    "E": 0.78,
    "A": 0.12,
    "N": 0.6
  },
  "RJB0088": {
    "O": 0.25,
    "C": 0.8,
    "E": 0.68,
    "A": 0.88,
    "N": 0.29
  },
  "OCB0805": {
    "O": 0.68,
    "C": 0.58,
    "E": 0.8,
    "A": 0.15,
    "N": 0.11
  },
  "ETR0428": {
    "O": 0.65,
    "C": 0.28,
    "E": 0.75,
    "A": 0.25,
    "N": 0.17
  },
  "IKP0472": {
    "O": 0.55,
    "C": 0.0,
    "E": 0.68,
    "A": 0.7,
    "N": 0.49
  },
  "LHB0967": {
    "O": 0.68,
    "C": 0.7,
    "E": 0.78,
    "A": 0.93,
    "N": 0.54
  },
  "CCM0467": {
    "O": 0.82,
    "C": 0.75,
    "E": 0.23,
    "A": 0.4,
    "N": 0.31
  },
  "GKO0078": {
    "O": 0.85,
    "C": 0.9,
    "E": 0.28,
    "A": 0.35,
    "N": 0.43
  },
  "GNS0178": {
    "O": 0.5,
    "C": 0.17,
    "E": 0.8,
    "A": 0.4,
    "N": 0.54
  },
  "SSS0345": {
    "O": 0.75,
    "C": 0.28,
    "E": 0.7,
    "A": 0.15,
    "N": 0.17
  },
  "LOM0086": {
    "O": 0.2,
    "C": 0.0,
    "E": 0.6,
    "A": 0.33,
    "N": 0.54
  },
  "SSR0278": {
    "O": 0.6,
    "C": 0.55,
    "E": 0.88,
    "A": 0.12,
    "N": 0.29
  },
  "ALH0402": {
    "O": 0.82,
    "C": 0.33,
    "E": 0.82,
    "A": 0.9,
    "N": 0.51
  },
  "AKK0329": {
    "O": 0.88,
    "C": 0.3,
    "E": 0.38,
    "A": 0.73,
    "N": 0.23
  },
  "EWH0191": {
    "O": 0.58,
    "C": 0.17,
    "E": 0.3,
    "A": 0.33,
    "N": 0.37
  },
  "TVS0050": {
    "O": 0.75,
    "C": 0.7,
    "E": 0.2,
    "A": 0.5,
    "N": 0.43
  },
  "TUC0632": {
    "O": 0.7,
    "C": 0.85,
    "E": 0.0,
    "A": 0.07,
    "N": 0.49
  },
  "SKG0759": {
    "O": 0.3,
    "C": 0.12,
    "E": 0.82,
    "A": 0.78,
    "N": 0.34
  },
  "IMG0320": {
    "O": 0.68,
    "C": 0.1,
    "E": 0.05,
    "A": 0.35,
    "N": 0.26
  },
  "BBG0325": {
    "O": 0.78,
    "C": 1.0,
    "E": 0.5,
    "A": 0.68,
    "N": 0.74
  },
  "CTW0500": {
    "O": 0.7,
    "C": 0.65,
    "E": 0.25,
    "A": 0.62,
    "N": 0.6
  },
  "SBN0495": {
    "O": 0.73,
    "C": 0.3,
    "E": 0.82,
    "A": 0.35,
    "N": 0.2
  },
  "ELH0960": {
    "O": 0.75,
    "C": 0.82,
    "E": 0.4,
    "A": 0.78,
    "N": 0.23
  },
  "BMS0877": {
    "O": 0.53,
    "C": 1.0,
    "E": 0.03,
    "A": 0.82,
    "N": 0.54
  },
  "TSG0906": {
    "O": 0.78,
    "C": 0.28,
    "E": 0.75,
    "A": 0.45,
    "N": 0.4
  },
  "RKD0604": {
    "O": 0.17,
    "C": 0.9,
    "E": 0.65,
    "A": 0.7,
    "N": 0.49
  },
  "JMK0099": {
    "O": 0.75,
    "C": 0.68,
    "E": 0.78,
    "A": 0.78,
    "N": 0.31
  },
  "MKP0861": {
    "O": 0.65,
    "C": 0.8,
    "E": 0.73,
    "A": 0.6,
    "N": 0.43
  },
  "HIW0536": {
    "O": 0.73,
    "C": 1.0,
    "E": 0.38,
    "A": 0.35,
    "N": 0.17
  },
  "CTR0697": {
    "O": 0.65,
    "C": 0.12,
    "E": 0.58,
    "A": 0.38,
    "N": 0.57
  },
  "BHC0665": {
    "O": 0.1,
    "C": 0.28,
    "E": 0.05,
    "A": 0.05,
    "N": 0.51
  },
  "DCH0843": {
    "O": 0.25,
    "C": 0.53,
    "E": 0.03,
    "A": 0.2,
    "N": 0.63
  },
  "WIF0691": {
    "O": 0.58,
    "C": 0.73,
    "E": 0.68,
    "A": 0.5,
    "N": 0.29
  },
  "HWM0342": {
    "O": 0.88,
    "C": 0.85,
    "E": 0.78,
    "A": 0.73,
    "N": 0.57
  },
  "MNC0717": {
    "O": 0.5,
    "C": 0.68,
    "E": 0.3,
    "A": 0.3,
    "N": 0.57
  },
  "ARB0881": {
    "O": 0.7,
    "C": 0.9,
    "E": 0.82,
    "A": 0.0,
    "N": 0.6
  },
  "AHC0142": {
    "O": 0.6,
    "C": 0.33,
    "E": 0.75,
    "A": 0.12,
    "N": 0.34
  },
  "ZFM0468": {
    "O": 0.62,
    "C": 0.15,
    "E": 0.25,
    "A": 0.88,
    "N": 0.46
  },
  "DIW0118": {
    "O": 0.68,
    "C": 0.17,
    "E": 0.23,
    "A": 0.68,
    "N": 0.34
  },
  "USH0199": {
    "O": 0.85,
    "C": 0.73,
    "E": 0.9,
    "A": 0.65,
    "N": 0.31
  },
  "MAD0753": {
    "O": 1.0,
    "C": 0.5,
    "E": 0.65,
    "A": 0.78,
    "N": 0.54
  },
  "KDS0349": {
    "O": 0.2,
    "C": 0.33,
    "E": 0.25,
    "A": 0.55,
    "N": 0.43
  },
  "LJB0826": {
    "O": 0.7,
    "C": 0.28,
    "E": 0.73,
    "A": 0.12,
    "N": 0.51
  },
  "FKK0055": {
    "O": 0.9,
    "C": 0.15,
    "E": 0.68,
    "A": 0.15,
    "N": 0.37
  },
  "TAP0551": {
    "O": 0.38,
    "C": 0.17,
    "E": 0.42,
    "A": 0.25,
    "N": 0.23
  },
  "FPC0954": {
    "O": 0.3,
    "C": 0.38,
    "E": 1.0,
    "A": 0.25,
    "N": 0.37
  },
  "GBM0603": {
    "O": 0.73,
    "C": 0.8,
    "E": 0.8,
    "A": 0.35,
    "N": 0.66
  },
  "CXC0336": {
    "O": 0.33,
    "C": 0.23,
    "E": 0.6,
    "A": 0.62,
    "N": 0.57
  },
  "HMM0108": {
    "O": 0.58,
    "C": 0.78,
    "E": 0.17,
    "A": 0.82,
    "N": 0.31
  },
  "FDE0117": {
    "O": 0.7,
    "C": 0.68,
    "E": 0.55,
    "A": 0.78,
    "N": 0.4
  },
  "FUM0015": {
    "O": 0.58,
    "C": 0.2,
    "E": 0.2,
    "A": 0.9,
    "N": 0.51
  },
  "NAB0801": {
    "O": 0.45,
    "C": 0.6,
    "E": 0.0,
    "A": 0.78,
    "N": 0.43
  },
  "GJT0386": {
    "O": 0.35,
    "C": 0.07,
    "E": 0.97,
    "A": 0.6,
    "N": 0.34
  },
  "KAC0124": {
    "O": 0.58,
    "C": 0.1,
    "E": 0.5,
    "A": 0.2,
    "N": 0.54
  },
  "RGH0728": {
    "O": 0.23,
    "C": 0.25,
    "E": 0.68,
    "A": 0.2,
    "N": 0.43
  },
  "CCR0863": {
    "O": 0.25,
    "C": 0.5,
    "E": 0.68,
    "A": 0.1,
    "N": 0.43
  },
  "TTD1000": {
    "O": 0.6,
    "C": 0.6,
    "E": 0.35,
    "A": 0.75,
    "N": 0.43
  },
  "OKB0439": {
    "O": 0.78,
    "C": 0.8,
    "E": 0.5,
    "A": 0.38,
    "N": 0.37
  },
  "XAA0104": {
    "O": 0.78,
    "C": 0.75,
    "E": 0.1,
    "A": 0.7,
    "N": 0.8
  },
  "RFP0380": {
    "O": 0.73,
    "C": 0.73,
    "E": 0.25,
    "A": 0.25,
    "N": 0.51
  },
  "JTS0389": {
    "O": 0.53,
    "C": 0.65,
    "E": 0.03,
    "A": 0.85,
    "N": 0.51
  },
  "CMS0454": {
    "O": 0.82,
    "C": 0.33,
    "E": 0.45,
    "A": 0.12,
    "N": 0.31
  },
  "JKB0126": {
    "O": 0.82,
    "C": 0.35,
    "E": 0.23,
    "A": 0.58,
    "N": 0.4
  },
  "LAM0911": {
    "O": 0.8,
    "C": 0.82,
    "E": 0.42,
    "A": 0.7,
    "N": 0.23
  },
  "GCC0744": {
    "O": 0.62,
    "C": 0.8,
    "E": 0.12,
    "A": 0.38,
    "N": 0.49
  },
  "CLH0703": {
    "O": 0.95,
    "C": 0.78,
    "E": 0.93,
    "A": 0.45,
    "N": 0.43
  },
  "KMW0545": {
    "O": 0.23,
    "C": 0.15,
    "E": 0.2,
    "A": 0.33,
    "N": 0.51
  },
  "PSF0133": {
    "O": 0.8,
    "C": 0.75,
    "E": 0.03,
    "A": 0.65,
    "N": 0.54
  },
  "NHH0185": {
    "O": 0.78,
    "C": 0.82,
    "E": 0.23,
    "A": 0.28,
    "N": 0.54
  },
  "NCE0097": {
    "O": 0.95,
    "C": 0.65,
    "E": 0.25,
    "A": 0.03,
    "N": 0.6
  },
  "CCL0068": {
    "O": 0.07,
    "C": 0.15,
    "E": 0.33,
    "A": 0.23,
    "N": 0.26
  },
  "AJC0840": {
    "O": 0.1,
    "C": 0.35,
    "E": 0.23,
    "A": 0.58,
    "N": 0.66
  },
  "GCC0945": {
    "O": 0.5,
    "C": 0.73,
    "E": 0.2,
    "A": 0.38,
    "N": 0.37
  },
  "NAB0903": {
    "O": 0.85,
    "C": 0.5,
    "E": 0.23,
    "A": 0.5,
    "N": 0.66
  },
  "AOS0987": {
    "O": 0.15,
    "C": 0.55,
    "E": 0.75,
    "A": 0.5,
    "N": 0.37
  },
  "JAD0609": {
    "O": 0.2,
    "C": 0.33,
    "E": 0.4,
    "A": 0.65,
    "N": 0.54
  },
  "AMW0392": {
    "O": 0.93,
    "C": 0.93,
    "E": 0.3,
    "A": 0.85,
    "N": 0.34
  },
  "FIR0920": {
    "O": 0.75,
    "C": 0.03,
    "E": 0.85,
    "A": 0.25,
    "N": 0.37
  },
  "RNP0211": {
    "O": 0.73,
    "C": 0.12,
    "E": 0.38,
    "A": 0.75,
    "N": 0.46
  },
  "RHY0079": {
    "O": 0.25,
    "C": 0.23,
    "E": 0.1,
    "A": 0.28,
    "N": 0.34
  },
  "CLS0296": {
    "O": 0.42,
    "C": 0.15,
    "E": 0.38,
    "A": 0.2,
    "N": 0.54
  },
  "JSA0775": {
    "O": 1.0,
    "C": 0.9,
    "E": 0.8,
    "A": 0.23,
    "N": 0.54
  },
  "RDM0115": {
    "O": 0.8,
    "C": 0.17,
    "E": 0.73,
    "A": 0.12,
    "N": 0.46
  },
  "JKM0303": {
    "O": 0.9,
    "C": 0.0,
    "E": 0.85,
    "A": 0.12,
    "N": 0.6
  },
  "IJM0139": {
    "O": 0.88,
    "C": 0.17,
    "E": 0.12,
    "A": 0.5,
    "N": 0.6
  },
  "SVL0940": {
    "O": 0.12,
    "C": 0.8,
    "E": 0.4,
    "A": 0.12,
    "N": 0.57
  },
  "LDG0459": {
    "O": 0.25,
    "C": 0.78,
    "E": 0.0,
    "A": 1.0,
    "N": 0.57
  },
  "ROB0272": {
    "O": 0.73,
    "C": 0.88,
    "E": 0.33,
    "A": 0.78,
    "N": 0.57
  },
  "LNS0989": {
    "O": 0.6,
    "C": 0.7,
    "E": 0.88,
    "A": 0.5,
    "N": 0.49
  },
  "CNM0800": {
    "O": 0.55,
    "C": 0.03,
    "E": 0.75,
    "A": 0.7,
    "N": 0.29
  },
  "HGN0287": {
    "O": 0.88,
    "C": 0.5,
    "E": 0.2,
    "A": 0.2,
    "N": 0.37
  },
  "KMS0657": {
    "O": 0.17,
    "C": 0.53,
    "E": 0.28,
    "A": 0.17,
    "N": 0.43
  },
  "BMG0917": {
    "O": 0.82,
    "C": 0.65,
    "E": 0.78,
    "A": 0.33,
    "N": 0.57
  },
  "HVB0037": {
    "O": 0.17,
    "C": 0.8,
    "E": 0.78,
    "A": 0.85,
    "N": 0.34
  },
  "PNH0761": {
    "O": 0.65,
    "C": 0.97,
    "E": 0.42,
    "A": 0.55,
    "N": 0.46
  },
  "JLW0053": {
    "O": 0.8,
    "C": 0.78,
    "E": 0.2,
    "A": 0.7,
    "N": 0.49
  },
  "JNA0559": {
    "O": 0.0,
    "C": 0.0,
    "E": 0.78,
    "A": 0.0,
    "N": 0.49
  },
  "OYM0026": {
    "O": 0.33,
    "C": 0.4,
    "E": 0.2,
    "A": 0.65,
    "N": 0.4
  },
  "NIH0969": {
    "O": 0.82,
    "C": 0.38,
    "E": 0.82,
    "A": 0.3,
    "N": 0.23
  },
  "RCC0617": {
    "O": 0.58,
    "C": 1.0,
    "E": 0.07,
    "A": 0.05,
    "N": 0.37
  },
  "GJD0298": {
    "O": 0.82,
    "C": 0.73,
    "E": 0.05,
    "A": 0.75,
    "N": 0.37
  },
  "MLL0598": {
    "O": 0.85,
    "C": 0.17,
    "E": 0.33,
    "A": 0.97,
    "N": 0.43
  },
  "DSM0591": {
    "O": 0.25,
    "C": 0.62,
    "E": 0.2,
    "A": 0.82,
    "N": 0.6
  },
  "BTL0226": {
    "O": 0.65,
    "C": 0.85,
    "E": 0.68,
    "A": 0.7,
    "N": 0.49
  },
  "SBN0971": {
    "O": 0.78,
    "C": 0.75,
    "E": 0.17,
    "A": 0.93,
    "N": 0.46
  },
  "CCW0524": {
    "O": 0.75,
    "C": 0.38,
    "E": 0.25,
    "A": 0.28,
    "N": 0.31
  },
  "IWM0816": {
    "O": 0.62,
    "C": 0.8,
    "E": 1.0,
    "A": 0.85,
    "N": 0.4
  },
  "JOL0024": {
    "O": 1.0,
    "C": 0.75,
    "E": 0.35,
    "A": 0.28,
    "N": 0.43
  },
  "ENL0100": {
    "O": 0.73,
    "C": 0.2,
    "E": 0.8,
    "A": 0.62,
    "N": 0.2
  },
  "TIW0299": {
    "O": 0.6,
    "C": 0.23,
    "E": 0.23,
    "A": 0.05,
    "N": 0.49
  },
  "ZSK0258": {
    "O": 0.7,
    "C": 0.62,
    "E": 0.28,
    "A": 0.68,
    "N": 0.31
  },
  "CGF0337": {
    "O": 0.55,
    "C": 0.5,
    "E": 0.82,
    "A": 0.12,
    "N": 0.49
  },
  "EHB0420": {
    "O": 0.88,
    "C": 0.8,
    "E": 0.7,
    "A": 0.17,
    "N": 0.17
  },
  "RGN0408": {
    "O": 0.03,
    "C": 0.28,
    "E": 0.3,
    "A": 0.3,
    "N": 0.51
  },
  "FHO0630": {
    "O": 0.45,
    "C": 0.85,
    "E": 0.33,
    "A": 0.05,
    "N": 0.34
  },
  "JKJ0698": {
    "O": 0.15,
    "C": 0.7,
    "E": 0.15,
    "A": 0.3,
    "N": 0.4
  },
  "SCF0608": {
    "O": 0.62,
    "C": 0.2,
    "E": 0.8,
    "A": 0.8,
    "N": 0.63
  },
  "BVC0790": {
    "O": 0.35,
    "C": 0.2,
    "E": 0.2,
    "A": 0.65,
    "N": 0.69
  },
  "NRF0137": {
    "O": 0.0,
    "C": 0.97,
    "E": 0.7,
    "A": 0.17,
    "N": 0.51
  },
  "HDD0789": {
    "O": 0.85,
    "C": 0.73,
    "E": 0.5,
    "A": 0.0,
    "N": 0.43
  },
  "IEB0153": {
    "O": 0.85,
    "C": 0.38,
    "E": 0.73,
    "A": 0.35,
    "N": 0.63
  },
  "ICH0294": {
    "O": 0.55,
    "C": 0.42,
    "E": 0.25,
    "A": 0.75,
    "N": 0.34
  },
  "ZSL0305": {
    "O": 0.28,
    "C": 0.4,
    "E": 0.2,
    "A": 0.78,
    "N": 0.51
  },
  "AJP0723": {
    "O": 0.35,
    "C": 0.48,
    "E": 0.17,
    "A": 0.05,
    "N": 0.43
  },
  "GDF0704": {
    "O": 0.38,
    "C": 0.07,
    "E": 0.28,
    "A": 0.48,
    "N": 0.63
  },
  "TJD0996": {
    "O": 0.6,
    "C": 0.3,
    "E": 0.8,
    "A": 0.15,
    "N": 0.51
  },
  "OMS0101": {
    "O": 0.25,
    "C": 0.05,
    "E": 0.28,
    "A": 0.3,
    "N": 0.43
  },
  "BCM0653": {
    "O": 0.88,
    "C": 0.6,
    "E": 0.78,
    "A": 0.2,
    "N": 0.49
  },
  "BDB0453": {
    "O": 0.78,
    "C": 0.8,
    "E": 0.42,
    "A": 0.78,
    "N": 0.34
  },
  "NCK0421": {
    "O": 0.75,
    "C": 0.78,
    "E": 0.2,
    "A": 0.82,
    "N": 0.29
  },
  "LPH0572": {
    "O": 0.75,
    "C": 0.07,
    "E": 0.17,
    "A": 0.7,
    "N": 0.63
  },
  "MFV0897": {
    "O": 0.2,
    "C": 0.07,
    "E": 0.33,
    "A": 0.38,
    "N": 0.54
  },
  "MAH0149": {
    "O": 0.78,
    "C": 0.73,
    "E": 0.7,
    "A": 0.42,
    "N": 0.74
  },
  "ECR0822": {
    "O": 0.15,
    "C": 0.23,
    "E": 0.17,
    "A": 0.33,
    "N": 0.43
  },
  "POB0343": {
    "O": 0.9,
    "C": 0.23,
    "E": 0.85,
    "A": 0.42,
    "N": 0.57
  },
  "IRT0491": {
    "O": 0.17,
    "C": 0.5,
    "E": 0.42,
    "A": 0.78,
    "N": 0.51
  },
  "HKI0171": {
    "O": 0.53,
    "C": 0.17,
    "E": 0.5,
    "A": 0.88,
    "N": 0.37
  },
  "DIB0285": {
    "O": 0.07,
    "C": 0.88,
    "E": 0.17,
    "A": 1.0,
    "N": 0.43
  },
  "IAR0694": {
    "O": 0.05,
    "C": 0.17,
    "E": 0.85,
    "A": 0.75,
    "N": 0.57
  },
  "CMM0487": {
    "O": 0.73,
    "C": 0.3,
    "E": 0.8,
    "A": 0.75,
    "N": 0.46
  },
  "LCC0819": {
    "O": 0.55,
    "C": 0.1,
    "E": 0.03,
    "A": 0.12,
    "N": 0.37
  },
  "AGB0643": {
    "O": 0.55,
    "C": 0.73,
    "E": 0.25,
    "A": 0.85,
    "N": 0.37
  },
  "PID0426": {
    "O": 0.82,
    "C": 0.23,
    "E": 0.73,
    "A": 0.85,
    "N": 0.26
  },
  "HLM0933": {
    "O": 0.65,
    "C": 0.35,
    "E": 0.33,
    "A": 0.82,
    "N": 0.46
  },
  "KRL0062": {
    "O": 0.68,
    "C": 0.15,
    "E": 0.17,
    "A": 0.25,
    "N": 0.54
  },
  "MPM0220": {
    "O": 0.62,
    "C": 0.25,
    "E": 0.8,
    "A": 0.3,
    "N": 0.17
  },
  "JDB0169": {
    "O": 0.25,
    "C": 0.1,
    "E": 0.33,
    "A": 0.95,
    "N": 0.54
  },
  "AAS0442": {
    "O": 0.65,
    "C": 0.82,
    "E": 0.3,
    "A": 0.3,
    "N": 0.49
  },
  "ZJS0269": {
    "O": 0.5,
    "C": 0.6,
    "E": 0.15,
    "A": 0.62,
    "N": 0.37
  },
  "CJM0521": {
    "O": 0.07,
    "C": 0.2,
    "E": 0.68,
    "A": 0.2,
    "N": 0.29
  },
  "MDH0580": {
    "O": 0.78,
    "C": 0.68,
    "E": 0.2,
    "A": 0.75,
    "N": 0.49
  },
  "JRS0362": {
    "O": 1.0,
    "C": 1.0,
    "E": 0.1,
    "A": 0.68,
    "N": 0.29
  },
  "WXH0872": {
    "O": 0.17,
    "C": 0.25,
    "E": 0.23,
    "A": 0.28,
    "N": 0.31
  },
  "MHA0798": {
    "O": 0.03,
    "C": 0.42,
    "E": 0.17,
    "A": 0.3,
    "N": 0.74
  },
  "JZD0888": {
    "O": 0.25,
    "C": 0.25,
    "E": 0.5,
    "A": 0.1,
    "N": 0.46
  },
  "HDD0806": {
    "O": 0.93,
    "C": 0.45,
    "E": 0.65,
    "A": 0.23,
    "N": 0.69
  },
  "BSB0990": {
    "O": 0.6,
    "C": 0.85,
    "E": 0.07,
    "A": 0.82,
    "N": 0.66
  },
  "ALC0788": {
    "O": 0.6,
    "C": 0.2,
    "E": 0.12,
    "A": 0.65,
    "N": 0.6
  },
  "JCR0921": {
    "O": 0.93,
    "C": 0.9,
    "E": 0.53,
    "A": 0.75,
    "N": 0.57
  },
  "RRA0938": {
    "O": 0.62,
    "C": 0.65,
    "E": 0.28,
    "A": 0.7,
    "N": 0.43
  },
  "SHW0578": {
    "O": 0.73,
    "C": 0.8,
    "E": 0.1,
    "A": 0.97,
    "N": 0.49
  },
  "GCL0016": {
    "O": 0.88,
    "C": 0.55,
    "E": 0.25,
    "A": 0.35,
    "N": 0.57
  },
  "GOK0238": {
    "O": 0.58,
    "C": 0.82,
    "E": 0.42,
    "A": 0.75,
    "N": 0.54
  },
  "BCB0679": {
    "O": 0.9,
    "C": 0.65,
    "E": 0.73,
    "A": 0.53,
    "N": 0.49
  },
  "IHK0841": {
    "O": 0.62,
    "C": 0.33,
    "E": 0.78,
    "A": 0.45,
    "N": 0.43
  },
  "SAP0867": {
    "O": 0.07,
    "C": 0.38,
    "E": 0.82,
    "A": 0.23,
    "N": 0.46
  },
  "ALD0529": {
    "O": 0.62,
    "C": 0.28,
    "E": 0.23,
    "A": 0.28,
    "N": 0.37
  },
  "KRG0158": {
    "O": 0.6,
    "C": 0.7,
    "E": 0.8,
    "A": 0.1,
    "N": 0.37
  },
  "TJB0302": {
    "O": 0.8,
    "C": 0.93,
    "E": 0.35,
    "A": 0.75,
    "N": 0.43
  },
  "ILC0838": {
    "O": 0.75,
    "C": 0.65,
    "E": 0.8,
    "A": 0.15,
    "N": 0.54
  },
  "RIH0777": {
    "O": 0.4,
    "C": 0.85,
    "E": 0.23,
    "A": 0.15,
    "N": 0.37
  },
  "HCW0419": {
    "O": 0.75,
    "C": 0.28,
    "E": 0.62,
    "A": 0.6,
    "N": 0.6
  },
  "DAL0673": {
    "O": 0.73,
    "C": 0.62,
    "E": 0.9,
    "A": 0.78,
    "N": 0.63
  },
  "RMS0266": {
    "O": 0.58,
    "C": 0.75,
    "E": 0.38,
    "A": 0.33,
    "N": 0.66
  },
  "KDT0346": {
    "O": 0.65,
    "C": 0.78,
    "E": 0.0,
    "A": 0.3,
    "N": 0.54
  },
  "KAL0395": {
    "O": 0.07,
    "C": 0.35,
    "E": 0.3,
    "A": 0.45,
    "N": 0.43
  },
  "ARD0509": {
    "O": 1.0,
    "C": 0.75,
    "E": 0.62,
    "A": 0.55,
    "N": 0.51
  },
  "BTL0722": {
    "O": 0.73,
    "C": 0.78,
    "E": 0.65,
    "A": 0.17,
    "N": 1.0
  },
  "WPE0538": {
    "O": 0.28,
    "C": 0.15,
    "E": 0.33,
    "A": 0.3,
    "N": 0.6
  },
  "CLF0852": {
    "O": 0.65,
    "C": 0.88,
    "E": 0.45,
    "A": 0.2,
    "N": 0.34
  },
  "HJA0018": {
    "O": 0.73,
    "C": 0.82,
    "E": 0.93,
    "A": 0.68,
    "N": 0.51
  },
  "MIM0712": {
    "O": 0.15,
    "C": 0.12,
    "E": 0.73,
    "A": 0.33,
    "N": 0.23
  },
  "CEJ0109": {
    "O": 0.28,
    "C": 0.9,
    "E": 0.17,
    "A": 0.17,
    "N": 0.51
  },
  "JCW0858": {
    "O": 0.1,
    "C": 0.62,
    "E": 0.3,
    "A": 0.78,
    "N": 0.71
  },
  "DFR0218": {
    "O": 0.88,
    "C": 0.1,
    "E": 0.3,
    "A": 0.68,
    "N": 0.37
  },
  "BAL0044": {
    "O": 0.1,
    "C": 0.78,
    "E": 0.4,
    "A": 0.85,
    "N": 0.46
  },
  "ASS0206": {
    "O": 0.05,
    "C": 0.2,
    "E": 0.25,
    "A": 0.45,
    "N": 0.46
  },
  "IUB0565": {
    "O": 0.85,
    "C": 0.73,
    "E": 0.62,
    "A": 0.3,
    "N": 0.46
  },
  "ASG0048": {
    "O": 0.78,
    "C": 0.65,
    "E": 0.23,
    "A": 0.35,
    "N": 0.66
  },
  "TET0621": {
    "O": 0.5,
    "C": 0.68,
    "E": 0.85,
    "A": 0.55,
    "N": 0.37
  },
  "ARA0252": {
    "O": 0.73,
    "C": 0.73,
    "E": 0.42,
    "A": 0.28,
    "N": 0.6
  },
  "AMR0318": {
    "O": 0.88,
    "C": 1.0,
    "E": 0.17,
    "A": 0.38,
    "N": 0.2
  },
  "WTF0387": {
    "O": 0.75,
    "C": 0.33,
    "E": 0.75,
    "A": 0.38,
    "N": 0.29
  },
  "AJL0462": {
    "O": 0.15,
    "C": 0.35,
    "E": 0.85,
    "A": 0.53,
    "N": 0.4
  },
  "SDF0017": {
    "O": 0.03,
    "C": 0.75,
    "E": 0.73,
    "A": 0.2,
    "N": 0.46
  },
  "RDM0150": {
    "O": 0.73,
    "C": 0.12,
    "E": 0.68,
    "A": 0.4,
    "N": 0.46
  },
  "HKF0831": {
    "O": 0.33,
    "C": 0.8,
    "E": 0.97,
    "A": 0.28,
    "N": 0.29
  },
  "DGF0443": {
    "O": 0.73,
    "C": 0.85,
    "E": 0.2,
    "A": 0.45,
    "N": 0.54
  },
  "CAB0614": {
    "O": 0.17,
    "C": 0.7,
    "E": 0.3,
    "A": 0.05,
    "N": 0.57
  },
  "DBG0261": {
    "O": 0.88,
    "C": 0.93,
    "E": 0.17,
    "A": 0.65,
    "N": 0.4
  },
  "ZDW0859": {
    "O": 0.73,
    "C": 0.88,
    "E": 0.4,
    "A": 0.78,
    "N": 0.51
  },
  "UCH0519": {
    "O": 0.58,
    "C": 0.75,
    "E": 0.25,
    "A": 0.93,
    "N": 0.4
  },
  "CAC0889": {
    "O": 0.9,
    "C": 0.97,
    "E": 0.55,
    "A": 0.78,
    "N": 0.37
  },
  "EHD0584": {
    "O": 0.7,
    "C": 0.75,
    "E": 0.8,
    "A": 0.82,
    "N": 0.23
  },
  "OLB0749": {
    "O": 0.82,
    "C": 0.62,
    "E": 0.25,
    "A": 0.73,
    "N": 0.63
  },
  "BWH0813": {
    "O": 0.65,
    "C": 0.65,
    "E": 0.58,
    "A": 0.25,
    "N": 0.46
  },
  "DMG0358": {
    "O": 0.23,
    "C": 0.73,
    "E": 0.1,
    "A": 0.38,
    "N": 0.43
  },
  "MAE0331": {
    "O": 0.65,
    "C": 0.73,
    "E": 0.2,
    "A": 0.05,
    "N": 0.4
  },
  "AMD0077": {
    "O": 0.33,
    "C": 0.23,
    "E": 0.05,
    "A": 0.38,
    "N": 0.31
  },
  "XLB0710": {
    "O": 0.9,
    "C": 0.7,
    "E": 0.73,
    "A": 0.65,
    "N": 0.17
  },
  "DAG0558": {
    "O": 0.25,
    "C": 0.15,
    "E": 0.68,
    "A": 0.38,
    "N": 0.34
  },
  "WLV0566": {
    "O": 0.0,
    "C": 0.23,
    "E": 0.7,
    "A": 0.35,
    "N": 0.71
  },
  "EHB0824": {
    "O": 0.9,
    "C": 0.73,
    "E": 0.3,
    "A": 0.85,
    "N": 0.49
  },
  "FBW0747": {
    "O": 0.82,
    "C": 0.88,
    "E": 0.62,
    "A": 0.38,
    "N": 0.4
  },
  "SNC0187": {
    "O": 0.75,
    "C": 0.78,
    "E": 0.8,
    "A": 0.5,
    "N": 0.37
  },
  "IBB0359": {
    "O": 0.95,
    "C": 0.58,
    "E": 0.28,
    "A": 0.82,
    "N": 0.69
  },
  "RAM0447": {
    "O": 0.62,
    "C": 0.05,
    "E": 0.33,
    "A": 0.88,
    "N": 0.71
  },
  "AJD0074": {
    "O": 0.23,
    "C": 0.68,
    "E": 0.88,
    "A": 0.3,
    "N": 0.57
  },
  "MSH0040": {
    "O": 0.78,
    "C": 0.03,
    "E": 0.85,
    "A": 0.42,
    "N": 0.49
  },
  "QJR0688": {
    "O": 0.23,
    "C": 0.2,
    "E": 0.3,
    "A": 0.4,
    "N": 0.6
  },
  "HTF0641": {
    "O": 0.7,
    "C": 0.35,
    "E": 0.2,
    "A": 0.3,
    "N": 0.4
  },
  "RDT0424": {
    "O": 0.7,
    "C": 0.85,
    "E": 0.23,
    "A": 0.6,
    "N": 0.4
  },
  "XRS0633": {
    "O": 0.6,
    "C": 0.73,
    "E": 0.73,
    "A": 0.75,
    "N": 0.26
  },
  "RLG0856": {
    "O": 0.2,
    "C": 0.65,
    "E": 0.8,
    "A": 0.2,
    "N": 0.34
  },
  "MLD0755": {
    "O": 0.35,
    "C": 0.2,
    "E": 0.23,
    "A": 0.82,
    "N": 0.66
  },
  "MOS0047": {
    "O": 0.97,
    "C": 0.73,
    "E": 0.35,
    "A": 0.6,
    "N": 0.26
  },
  "ETR0177": {
    "O": 0.2,
    "C": 0.12,
    "E": 0.78,
    "A": 0.4,
    "N": 0.71
  },
  "RYB0718": {
    "O": 0.23,
    "C": 0.2,
    "E": 0.8,
    "A": 0.07,
    "N": 0.2
  },
  "AAE0190": {
    "O": 0.65,
    "C": 0.5,
    "E": 0.1,
    "A": 1.0,
    "N": 0.43
  },
  "NAF0033": {
    "O": 0.6,
    "C": 0.75,
    "E": 0.23,
    "A": 0.62,
    "N": 0.43
  },
  "DVM0265": {
    "O": 0.93,
    "C": 0.75,
    "E": 0.0,
    "A": 0.35,
    "N": 0.49
  },
  "JFC0757": {
    "O": 0.53,
    "C": 0.28,
    "E": 0.7,
    "A": 0.65,
    "N": 0.69
  },
  "AOB0019": {
    "O": 0.03,
    "C": 0.17,
    "E": 0.07,
    "A": 0.35,
    "N": 0.4
  },
  "AIP0394": {
    "O": 0.17,
    "C": 0.15,
    "E": 0.7,
    "A": 0.1,
    "N": 0.34
  },
  "JJB0127": {
    "O": 0.4,
    "C": 0.28,
    "E": 0.7,
    "A": 0.5,
    "N": 0.51
  },
  "MCS0035": {
    "O": 0.8,
    "C": 0.17,
    "E": 0.7,
    "A": 0.12,
    "N": 0.54
  },
  "ABC0253": {
    "O": 0.28,
    "C": 0.12,
    "E": 0.78,
    "A": 0.5,
    "N": 0.4
  },
  "TQS0212": {
    "O": 0.1,
    "C": 0.8,
    "E": 0.88,
    "A": 0.25,
    "N": 0.37
  },
  "RSM0277": {
    "O": 0.68,
    "C": 0.7,
    "E": 0.25,
    "A": 1.0,
    "N": 0.23
  },
  "JER0404": {
    "O": 0.7,
    "C": 0.9,
    "E": 0.2,
    "A": 0.15,
    "N": 0.46
  },
  "CIG0052": {
    "O": 0.17,
    "C": 0.88,
    "E": 0.17,
    "A": 0.15,
    "N": 0.29
  },
  "IIW0249": {
    "O": 0.73,
    "C": 0.65,
    "E": 0.82,
    "A": 0.7,
    "N": 0.4
  },
  "HVF0067": {
    "O": 0.85,
    "C": 0.62,
    "E": 0.3,
    "A": 0.82,
    "N": 0.77
  },
  "HWW0436": {
    "O": 0.88,
    "C": 0.68,
    "E": 0.33,
    "A": 0.42,
    "N": 0.54
  },
  "PEV0323": {
    "O": 0.93,
    "C": 0.6,
    "E": 0.75,
    "A": 0.3,
    "N": 0.43
  },
  "PGO0433": {
    "O": 0.85,
    "C": 0.75,
    "E": 0.23,
    "A": 0.9,
    "N": 0.6
  },
  "MVB0515": {
    "O": 0.7,
    "C": 0.1,
    "E": 0.58,
    "A": 0.53,
    "N": 0.4
  },
  "TJG0582": {
    "O": 0.8,
    "C": 1.0,
    "E": 0.2,
    "A": 0.12,
    "N": 0.43
  },
  "SRH0155": {
    "O": 0.6,
    "C": 0.1,
    "E": 0.68,
    "A": 0.88,
    "N": 0.4
  },
  "IJM0444": {
    "O": 0.65,
    "C": 0.62,
    "E": 0.73,
    "A": 0.62,
    "N": 0.34
  },
  "CIM0271": {
    "O": 0.35,
    "C": 0.42,
    "E": 0.0,
    "A": 0.25,
    "N": 0.69
  },
  "CSL0949": {
    "O": 0.65,
    "C": 0.25,
    "E": 0.2,
    "A": 0.38,
    "N": 0.4
  },
  "AAN0823": {
    "O": 0.35,
    "C": 0.15,
    "E": 0.88,
    "A": 0.35,
    "N": 0.4
  },
  "JGT0221": {
    "O": 0.88,
    "C": 0.5,
    "E": 0.15,
    "A": 0.75,
    "N": 0.11
  },
  "AKH0758": {
    "O": 0.35,
    "C": 0.7,
    "E": 0.75,
    "A": 0.68,
    "N": 0.37
  },
  "HSG0818": {
    "O": 0.2,
    "C": 0.23,
    "E": 0.95,
    "A": 0.65,
    "N": 0.49
  },
  "MIL0255": {
    "O": 0.7,
    "C": 0.15,
    "E": 0.73,
    "A": 0.28,
    "N": 0.37
  },
  "JGM0934": {
    "O": 0.5,
    "C": 0.3,
    "E": 0.78,
    "A": 0.3,
    "N": 0.49
  },
  "KCO0122": {
    "O": 0.5,
    "C": 0.55,
    "E": 0.4,
    "A": 0.7,
    "N": 0.54
  },
  "SGB0140": {
    "O": 1.0,
    "C": 0.88,
    "E": 0.75,
    "A": 0.15,
    "N": 0.29
  },
  "NAF0326": {
    "O": 0.58,
    "C": 0.12,
    "E": 0.38,
    "A": 0.25,
    "N": 0.46
  },
  "IUY0279": {
    "O": 0.7,
    "C": 0.7,
    "E": 0.17,
    "A": 0.28,
    "N": 0.43
  },
  "EIM0156": {
    "O": 0.23,
    "C": 0.53,
    "E": 0.82,
    "A": 0.88,
    "N": 0.54
  },
  "ABH0663": {
    "O": 0.93,
    "C": 0.97,
    "E": 0.78,
    "A": 0.03,
    "N": 0.57
  },
  "EZT0640": {
    "O": 0.05,
    "C": 0.12,
    "E": 0.42,
    "A": 0.73,
    "N": 0.37
  },
  "BAK0964": {
    "O": 0.38,
    "C": 0.15,
    "E": 0.3,
    "A": 0.2,
    "N": 0.4
  },
  "JCC0225": {
    "O": 0.93,
    "C": 0.88,
    "E": 0.75,
    "A": 0.12,
    "N": 0.11
  },
  "EMW0105": {
    "O": 0.62,
    "C": 0.75,
    "E": 0.17,
    "A": 0.78,
    "N": 0.57
  },
  "KLH0596": {
    "O": 0.5,
    "C": 0.0,
    "E": 0.62,
    "A": 0.05,
    "N": 0.43
  },
  "SJF0094": {
    "O": 0.62,
    "C": 0.23,
    "E": 0.15,
    "A": 0.85,
    "N": 0.46
  },
  "CSJ0340": {
    "O": 0.88,
    "C": 0.35,
    "E": 0.23,
    "A": 0.7,
    "N": 0.31
  },
  "RMW0542": {
    "O": 0.17,
    "C": 0.28,
    "E": 0.25,
    "A": 0.07,
    "N": 0.77
  },
  "JHP0583": {
    "O": 0.68,
    "C": 0.38,
    "E": 0.75,
    "A": 0.8,
    "N": 0.66
  },
  "HSD0457": {
    "O": 0.7,
    "C": 0.23,
    "E": 0.25,
    "A": 0.8,
    "N": 0.37
  },
  "YWW0660": {
    "O": 0.73,
    "C": 0.62,
    "E": 0.68,
    "A": 0.0,
    "N": 0.63
  },
  "PGC0066": {
    "O": 0.55,
    "C": 0.73,
    "E": 0.45,
    "A": 0.82,
    "N": 0.34
  },
  "MSO0222": {
    "O": 0.55,
    "C": 0.05,
    "E": 0.73,
    "A": 0.9,
    "N": 0.4
  },
  "WDV0573": {
    "O": 0.95,
    "C": 0.65,
    "E": 0.07,
    "A": 0.53,
    "N": 0.54
  },
  "QRM0739": {
    "O": 0.58,
    "C": 0.03,
    "E": 0.4,
    "A": 0.48,
    "N": 0.46
  },
  "ASS0517": {
    "O": 0.65,
    "C": 0.62,
    "E": 0.93,
    "A": 0.85,
    "N": 0.51
  },
  "LUR0896": {
    "O": 0.12,
    "C": 0.03,
    "E": 0.93,
    "A": 0.82,
    "N": 0.4
  },
  "ESH0283": {
    "O": 0.85,
    "C": 0.5,
    "E": 0.62,
    "A": 0.2,
    "N": 0.49
  },
  "WBC0192": {
    "O": 0.93,
    "C": 0.65,
    "E": 0.73,
    "A": 0.73,
    "N": 0.37
  },
  "PLH0715": {
    "O": 0.8,
    "C": 0.68,
    "E": 0.23,
    "A": 0.68,
    "N": 0.43
  },
  "VSA0230": {
    "O": 0.93,
    "C": 0.12,
    "E": 0.38,
    "A": 0.1,
    "N": 0.43
  },
  "KJG0910": {
    "O": 0.68,
    "C": 0.0,
    "E": 0.53,
    "A": 0.2,
    "N": 0.43
  },
  "DBW0483": {
    "O": 0.17,
    "C": 0.15,
    "E": 0.38,
    "A": 0.28,
    "N": 0.66
  },
  "KBC0054": {
    "O": 0.8,
    "C": 0.82,
    "E": 0.17,
    "A": 0.78,
    "N": 0.51
  },
  "CSC0217": {
    "O": 0.75,
    "C": 0.12,
    "E": 0.5,
    "A": 0.7,
    "N": 0.4
  },
  "BRS0734": {
    "O": 0.55,
    "C": 0.73,
    "E": 0.93,
    "A": 0.0,
    "N": 0.46
  },
  "KNB0022": {
    "O": 0.3,
    "C": 0.7,
    "E": 0.88,
    "A": 0.15,
    "N": 0.46
  },
  "PIS0522": {
    "O": 0.85,
    "C": 0.4,
    "E": 0.95,
    "A": 0.75,
    "N": 0.6
  },
  "ADD0846": {
    "O": 0.2,
    "C": 0.23,
    "E": 0.38,
    "A": 0.05,
    "N": 0.6
  },
  "MAD0496": {
    "O": 0.6,
    "C": 0.5,
    "E": 0.75,
    "A": 0.8,
    "N": 0.29
  },
  "NKP0236": {
    "O": 0.88,
    "C": 0.78,
    "E": 0.23,
    "A": 0.75,
    "N": 0.49
  },
  "VLB0647": {
    "O": 0.95,
    "C": 0.75,
    "E": 0.8,
    "A": 0.93,
    "N": 0.29
  },
  "DKB0631": {
    "O": 0.6,
    "C": 0.2,
    "E": 0.1,
    "A": 0.9,
    "N": 0.49
  },
  "KES0729": {
    "O": 0.25,
    "C": 0.0,
    "E": 0.35,
    "A": 0.88,
    "N": 0.49
  },
  "IBB0696": {
    "O": 0.93,
    "C": 0.07,
    "E": 0.65,
    "A": 0.15,
    "N": 0.54
  },
  "BLL0929": {
    "O": 0.85,
    "C": 0.97,
    "E": 0.0,
    "A": 0.78,
    "N": 0.71
  },
  "ABC0174": {
    "O": 0.12,
    "C": 0.78,
    "E": 0.6,
    "A": 0.07,
    "N": 0.51
  },
  "HAH0248": {
    "O": 0.58,
    "C": 0.82,
    "E": 0.3,
    "A": 0.2,
    "N": 0.43
  },
  "NBC0412": {
    "O": 0.1,
    "C": 0.38,
    "E": 0.2,
    "A": 0.2,
    "N": 0.49
  },
  "CRP0456": {
    "O": 0.68,
    "C": 0.78,
    "E": 0.45,
    "A": 0.82,
    "N": 0.46
  },
  "JIG0128": {
    "O": 0.38,
    "C": 0.88,
    "E": 0.62,
    "A": 0.2,
    "N": 0.37
  },
  "IJR0825": {
    "O": 0.7,
    "C": 0.8,
    "E": 0.73,
    "A": 0.9,
    "N": 0.51
  },
  "XWD0923": {
    "O": 0.15,
    "C": 0.7,
    "E": 0.88,
    "A": 0.25,
    "N": 0.49
  },
  "LDD0560": {
    "O": 0.38,
    "C": 0.82,
    "E": 0.73,
    "A": 0.4,
    "N": 0.6
  },
  "ESH0135": {
    "O": 0.62,
    "C": 0.3,
    "E": 0.55,
    "A": 0.85,
    "N": 0.4
  },
  "RHO0732": {
    "O": 0.25,
    "C": 0.0,
    "E": 0.28,
    "A": 0.23,
    "N": 0.57
  },
  "DGW0752": {
    "O": 0.75,
    "C": 0.9,
    "E": 0.25,
    "A": 0.75,
    "N": 0.0
  },
  "HPR0585": {
    "O": 0.6,
    "C": 0.9,
    "E": 0.12,
    "A": 0.9,
    "N": 0.6
  },
  "TBT0461": {
    "O": 0.82,
    "C": 0.8,
    "E": 0.07,
    "A": 0.5,
    "N": 0.4
  },
  "SAK0375": {
    "O": 0.15,
    "C": 0.25,
    "E": 0.42,
    "A": 0.15,
    "N": 0.49
  },
  "BJH0811": {
    "O": 0.95,
    "C": 0.73,
    "E": 0.85,
    "A": 0.1,
    "N": 0.74
  },
  "TVS0006": {
    "O": 0.82,
    "C": 0.82,
    "E": 0.68,
    "A": 0.25,
    "N": 0.77
  },
  "FAW0032": {
    "O": 0.82,
    "C": 0.35,
    "E": 0.17,
    "A": 0.68,
    "N": 0.66
  },
  "WSR0241": {
    "O": 0.62,
    "C": 0.42,
    "E": 0.12,
    "A": 0.38,
    "N": 0.43
  },
  "LRW0970": {
    "O": 0.0,
    "C": 0.4,
    "E": 0.73,
    "A": 0.3,
    "N": 0.4
  },
  "ZMC0284": {
    "O": 0.8,
    "C": 0.58,
    "E": 0.78,
    "A": 0.5,
    "N": 0.49
  },
  "SAC0687": {
    "O": 0.25,
    "C": 0.97,
    "E": 0.68,
    "A": 0.23,
    "N": 0.23
  },
  "CKB0427": {
    "O": 0.7,
    "C": 0.7,
    "E": 0.65,
    "A": 0.82,
    "N": 0.66
  },
  "BTS0011": {
    "O": 0.38,
    "C": 0.8,
    "E": 0.15,
    "A": 0.38,
    "N": 0.43
  },
  "IIA0092": {
    "O": 0.73,
    "C": 0.5,
    "E": 0.8,
    "A": 0.1,
    "N": 0.37
  },
  "WKD0013": {
    "O": 0.8,
    "C": 0.65,
    "E": 0.75,
    "A": 0.42,
    "N": 0.57
  },
  "JNJ0556": {
    "O": 0.82,
    "C": 0.88,
    "E": 0.3,
    "A": 0.58,
    "N": 0.57
  },
  "TLH0648": {
    "O": 0.55,
    "C": 0.62,
    "E": 0.2,
    "A": 0.35,
    "N": 0.34
  },
  "IBP0883": {
    "O": 0.5,
    "C": 0.38,
    "E": 0.12,
    "A": 0.03,
    "N": 0.09
  },
  "WAS0254": {
    "O": 0.82,
    "C": 0.68,
    "E": 0.15,
    "A": 0.2,
    "N": 0.6
  },
  "QNP0216": {
    "O": 0.23,
    "C": 0.62,
    "E": 0.73,
    "A": 0.4,
    "N": 0.57
  },
  "KLM0639": {
    "O": 0.25,
    "C": 0.12,
    "E": 0.35,
    "A": 0.75,
    "N": 0.34
  },
  "AIB0948": {
    "O": 0.8,
    "C": 0.53,
    "E": 0.42,
    "A": 0.25,
    "N": 0.49
  },
  "RBB0485": {
    "O": 0.75,
    "C": 0.75,
    "E": 0.62,
    "A": 0.5,
    "N": 0.34
  },
  "RZC0746": {
    "O": 0.12,
    "C": 0.7,
    "E": 0.58,
    "A": 0.82,
    "N": 0.34
  },
  "MDM0976": {
    "O": 0.78,
    "C": 0.75,
    "E": 0.7,
    "A": 0.25,
    "N": 0.49
  },
  "XBN0229": {
    "O": 0.6,
    "C": 0.15,
    "E": 0.17,
    "A": 0.75,
    "N": 0.43
  },
  "SMH0291": {
    "O": 0.33,
    "C": 0.3,
    "E": 0.0,
    "A": 0.35,
    "N": 0.51
  },
  "MCD0125": {
    "O": 0.65,
    "C": 0.4,
    "E": 1.0,
    "A": 0.3,
    "N": 0.26
  },
  "MHG0244": {
    "O": 0.8,
    "C": 0.9,
    "E": 0.28,
    "A": 0.12,
    "N": 0.23
  },
  "RAS0432": {
    "O": 0.85,
    "C": 0.93,
    "E": 0.75,
    "A": 0.78,
    "N": 0.06
  },
  "EIP0997": {
    "O": 0.8,
    "C": 0.45,
    "E": 0.25,
    "A": 0.38,
    "N": 0.57
  },
  "EMW0772": {
    "O": 0.9,
    "C": 0.78,
    "E": 0.25,
    "A": 0.05,
    "N": 0.4
  },
  "SBQ0786": {
    "O": 0.78,
    "C": 0.17,
    "E": 0.23,
    "A": 0.85,
    "N": 0.57
  },
  "PDH0716": {
    "O": 0.75,
    "C": 0.15,
    "E": 0.1,
    "A": 0.0,
    "N": 0.29
  },
  "GZB0469": {
    "O": 0.9,
    "C": 0.73,
    "E": 0.3,
    "A": 0.88,
    "N": 0.4
  },
  "NMB0972": {
    "O": 0.88,
    "C": 0.3,
    "E": 0.17,
    "A": 0.25,
    "N": 0.43
  },
  "ONL0276": {
    "O": 0.95,
    "C": 0.9,
    "E": 0.17,
    "A": 0.78,
    "N": 0.17
  },
  "MBJ0312": {
    "O": 0.3,
    "C": 0.88,
    "E": 0.97,
    "A": 0.05,
    "N": 0.34
  },
  "DRR0242": {
    "O": 0.73,
    "C": 0.23,
    "E": 0.75,
    "A": 0.78,
    "N": 0.54
  },
  "AJH0175": {
    "O": 0.23,
    "C": 0.23,
    "E": 0.15,
    "A": 0.58,
    "N": 0.66
  },
  "LQP0508": {
    "O": 0.4,
    "C": 0.85,
    "E": 0.28,
    "A": 0.75,
    "N": 0.37
  },
  "DVW0103": {
    "O": 0.75,
    "C": 0.88,
    "E": 0.85,
    "A": 0.28,
    "N": 0.43
  },
  "SMB0804": {
    "O": 0.7,
    "C": 0.0,
    "E": 0.23,
    "A": 0.65,
    "N": 0.54
  },
  "KBG0549": {
    "O": 0.15,
    "C": 0.23,
    "E": 0.68,
    "A": 0.0,
    "N": 0.51
  },
  "BAH0875": {
    "O": 0.82,
    "C": 0.23,
    "E": 0.4,
    "A": 0.17,
    "N": 0.46
  },
  "SLT0907": {
    "O": 0.15,
    "C": 0.12,
    "E": 0.82,
    "A": 0.42,
    "N": 0.37
  },
  "JAV0361": {
    "O": 0.65,
    "C": 0.88,
    "E": 0.75,
    "A": 0.88,
    "N": 0.54
  },
  "COM0321": {
    "O": 0.7,
    "C": 0.2,
    "E": 0.6,
    "A": 0.2,
    "N": 0.37
  },
  "CCC0393": {
    "O": 0.62,
    "C": 0.5,
    "E": 0.75,
    "A": 0.15,
    "N": 0.34
  },
  "QSV0778": {
    "O": 0.17,
    "C": 0.33,
    "E": 0.65,
    "A": 0.62,
    "N": 0.54
  },
  "BMC0547": {
    "O": 0.78,
    "C": 0.2,
    "E": 0.3,
    "A": 0.28,
    "N": 0.6
  },
  "AWM0764": {
    "O": 0.93,
    "C": 0.68,
    "E": 0.73,
    "A": 0.8,
    "N": 0.63
  },
  "FXF0957": {
    "O": 0.62,
    "C": 0.38,
    "E": 0.93,
    "A": 0.65,
    "N": 0.4
  },
  "SVS0871": {
    "O": 0.33,
    "C": 0.12,
    "E": 0.6,
    "A": 0.45,
    "N": 0.54
  },
  "DJS0682": {
    "O": 0.3,
    "C": 0.33,
    "E": 0.65,
    "A": 0.07,
    "N": 0.46
  },
  "NHE0919": {
    "O": 0.38,
    "C": 0.15,
    "E": 0.55,
    "A": 0.28,
    "N": 0.29
  },
  "MPT0376": {
    "O": 0.23,
    "C": 0.68,
    "E": 0.78,
    "A": 0.95,
    "N": 0.6
  },
  "AQD0820": {
    "O": 0.78,
    "C": 0.53,
    "E": 0.42,
    "A": 0.35,
    "N": 0.71
  },
  "YEV0793": {
    "O": 0.75,
    "C": 0.68,
    "E": 0.8,
    "A": 0.12,
    "N": 0.23
  },
  "ZCF0590": {
    "O": 0.8,
    "C": 0.8,
    "E": 0.8,
    "A": 0.38,
    "N": 0.49
  },
  "KQC0708": {
    "O": 0.6,
    "C": 0.2,
    "E": 0.73,
    "A": 0.8,
    "N": 0.26
  },
  "LJR0523": {
    "O": 0.55,
    "C": 0.28,
    "E": 0.03,
    "A": 0.58,
    "N": 0.31
  },
  "CQH0701": {
    "O": 0.62,
    "C": 1.0,
    "E": 0.73,
    "A": 1.0,
    "N": 0.51
  },
  "PDW0259": {
    "O": 0.82,
    "C": 0.55,
    "E": 0.7,
    "A": 0.65,
    "N": 0.54
  },
  "FWM0707": {
    "O": 1.0,
    "C": 0.65,
    "E": 0.62,
    "A": 0.2,
    "N": 0.57
  },
  "HDS0367": {
    "O": 1.0,
    "C": 0.8,
    "E": 0.15,
    "A": 0.5,
    "N": 0.14
  },
  "JRH0455": {
    "O": 0.23,
    "C": 0.28,
    "E": 0.8,
    "A": 0.25,
    "N": 0.57
  },
  "SER0165": {
    "O": 0.25,
    "C": 0.12,
    "E": 0.35,
    "A": 0.17,
    "N": 0.37
  },
  "SBD0913": {
    "O": 0.88,
    "C": 0.15,
    "E": 0.23,
    "A": 0.23,
    "N": 0.8
  },
  "JKF0465": {
    "O": 0.0,
    "C": 0.68,
    "E": 0.05,
    "A": 0.17,
    "N": 0.51
  },
  "CFW0264": {
    "O": 0.23,
    "C": 0.55,
    "E": 0.17,
    "A": 0.25,
    "N": 0.37
  },
  "BNR0965": {
    "O": 0.93,
    "C": 0.23,
    "E": 0.12,
    "A": 0.25,
    "N": 0.23
  },
  "ASV0946": {
    "O": 0.62,
    "C": 0.05,
    "E": 0.9,
    "A": 0.17,
    "N": 0.34
  },
  "KNG0672": {
    "O": 0.28,
    "C": 0.75,
    "E": 0.2,
    "A": 0.25,
    "N": 0.37
  },
  "NNA0610": {
    "O": 0.28,
    "C": 0.62,
    "E": 0.2,
    "A": 0.82,
    "N": 0.34
  },
  "KQS0415": {
    "O": 0.62,
    "C": 0.8,
    "E": 0.07,
    "A": 0.1,
    "N": 0.57
  },
  "MHH0180": {
    "O": 0.23,
    "C": 0.78,
    "E": 0.62,
    "A": 0.0,
    "N": 0.43
  },
  "EGD0132": {
    "O": 0.68,
    "C": 0.7,
    "E": 0.58,
    "A": 0.12,
    "N": 0.23
  },
  "VTT0385": {
    "O": 0.1,
    "C": 0.4,
    "E": 0.17,
    "A": 0.65,
    "N": 0.4
  },
  "ASG0692": {
    "O": 0.4,
    "C": 0.75,
    "E": 0.78,
    "A": 0.33,
    "N": 0.37
  },
  "WPR0368": {
    "O": 0.95,
    "C": 0.6,
    "E": 0.75,
    "A": 0.17,
    "N": 0.49
  },
  "HAV0121": {
    "O": 0.9,
    "C": 0.82,
    "E": 0.7,
    "A": 0.68,
    "N": 0.37
  },
  "HCC0344": {
    "O": 0.38,
    "C": 0.03,
    "E": 0.78,
    "A": 0.4,
    "N": 0.23
  },
  "UBF0645": {
    "O": 0.6,
    "C": 0.25,
    "E": 0.6,
    "A": 0.33,
    "N": 0.49
  },
  "TSR0676": {
    "O": 0.82,
    "C": 0.75,
    "E": 0.4,
    "A": 0.23,
    "N": 0.54
  },
  "NKH0979": {
    "O": 0.5,
    "C": 0.73,
    "E": 0.8,
    "A": 0.3,
    "N": 0.6
  },
  "SXM0895": {
    "O": 0.1,
    "C": 0.2,
    "E": 0.12,
    "A": 0.58,
    "N": 0.31
  },
  "KCS0173": {
    "O": 0.73,
    "C": 0.25,
    "E": 1.0,
    "A": 0.25,
    "N": 0.46
  },
  "CCA0046": {
    "O": 0.65,
    "C": 0.82,
    "E": 0.38,
    "A": 0.12,
    "N": 0.4
  },
  "PMV0850": {
    "O": 0.33,
    "C": 0.73,
    "E": 0.05,
    "A": 0.8,
    "N": 0.26
  },
  "PKB0281": {
    "O": 0.73,
    "C": 0.05,
    "E": 0.85,
    "A": 0.4,
    "N": 0.31
  },
  "MIC0726": {
    "O": 0.55,
    "C": 0.78,
    "E": 0.82,
    "A": 0.17,
    "N": 0.26
  },
  "SDO0170": {
    "O": 0.62,
    "C": 0.93,
    "E": 0.3,
    "A": 0.88,
    "N": 0.34
  },
  "VAA0087": {
    "O": 0.65,
    "C": 0.85,
    "E": 0.8,
    "A": 0.2,
    "N": 0.26
  },
  "ELB0847": {
    "O": 0.05,
    "C": 0.17,
    "E": 0.15,
    "A": 0.23,
    "N": 0.4
  },
  "SBK0161": {
    "O": 0.1,
    "C": 0.42,
    "E": 0.33,
    "A": 0.78,
    "N": 0.71
  },
  "ASL0378": {
    "O": 0.12,
    "C": 0.12,
    "E": 0.78,
    "A": 0.28,
    "N": 0.37
  },
  "TLM0797": {
    "O": 0.82,
    "C": 0.8,
    "E": 0.6,
    "A": 0.33,
    "N": 0.63
  },
  "SOF0808": {
    "O": 0.88,
    "C": 0.75,
    "E": 0.7,
    "A": 0.3,
    "N": 0.37
  },
  "SGM0021": {
    "O": 0.78,
    "C": 0.05,
    "E": 0.4,
    "A": 0.78,
    "N": 0.54
  },
  "MYD0978": {
    "O": 0.73,
    "C": 0.55,
    "E": 0.65,
    "A": 0.07,
    "N": 0.51
  },
  "FBA0348": {
    "O": 0.78,
    "C": 0.85,
    "E": 0.75,
    "A": 0.65,
    "N": 0.37
  },
  "ARL0034": {
    "O": 0.78,
    "C": 0.73,
    "E": 0.42,
    "A": 0.28,
    "N": 0.34
  },
  "YJF0532": {
    "O": 0.75,
    "C": 0.62,
    "E": 0.33,
    "A": 0.93,
    "N": 0.34
  },
  "RJM0381": {
    "O": 0.78,
    "C": 0.93,
    "E": 0.85,
    "A": 0.78,
    "N": 0.31
  },
  "VSS0154": {
    "O": 0.82,
    "C": 0.97,
    "E": 0.0,
    "A": 0.75,
    "N": 0.46
  },
  "JMW0638": {
    "O": 0.82,
    "C": 0.28,
    "E": 0.5,
    "A": 0.2,
    "N": 0.46
  },
  "IKR0401": {
    "O": 0.75,
    "C": 0.8,
    "E": 0.35,
    "A": 0.15,
    "N": 0.43
  },
  "EMS0317": {
    "O": 0.12,
    "C": 0.28,
    "E": 0.85,
    "A": 0.0,
    "N": 0.49
  },
  "FTM0406": {
    "O": 0.53,
    "C": 0.12,
    "E": 0.7,
    "A": 0.15,
    "N": 0.57
  },
  "RAR0725": {
    "O": 0.55,
    "C": 0.55,
    "E": 0.38,
    "A": 0.25,
    "N": 0.6
  },
  "MNS0224": {
    "O": 0.9,
    "C": 0.28,
    "E": 0.3,
    "A": 0.88,
    "N": 0.46
  },
  "WVB0539": {
    "O": 0.82,
    "C": 0.15,
    "E": 0.2,
    "A": 0.8,
    "N": 0.49
  },
  "SSG0250": {
    "O": 0.62,
    "C": 0.75,
    "E": 0.25,
    "A": 0.65,
    "N": 0.31
  },
  "MLM0950": {
    "O": 0.35,
    "C": 0.25,
    "E": 0.48,
    "A": 0.33,
    "N": 0.63
  },
  "HPH0075": {
    "O": 0.75,
    "C": 0.8,
    "E": 0.95,
    "A": 0.38,
    "N": 0.4
  },
  "VMJ0546": {
    "O": 0.25,
    "C": 0.68,
    "E": 0.48,
    "A": 0.73,
    "N": 0.34
  },
  "NLO0131": {
    "O": 0.23,
    "C": 0.07,
    "E": 0.9,
    "A": 0.75,
    "N": 0.43
  },
  "PES0085": {
    "O": 0.62,
    "C": 0.35,
    "E": 0.2,
    "A": 0.5,
    "N": 0.23
  },
  "OHC0973": {
    "O": 0.8,
    "C": 0.35,
    "E": 0.8,
    "A": 0.17,
    "N": 0.6
  },
  "NMF0780": {
    "O": 0.85,
    "C": 0.7,
    "E": 0.65,
    "A": 0.25,
    "N": 0.57
  },
  "LEM0605": {
    "O": 0.9,
    "C": 1.0,
    "E": 0.75,
    "A": 0.73,
    "N": 0.34
  },
  "BEC0505": {
    "O": 0.62,
    "C": 0.28,
    "E": 0.5,
    "A": 0.23,
    "N": 0.51
  },
  "OLF0504": {
    "O": 0.78,
    "C": 0.82,
    "E": 0.25,
    "A": 0.78,
    "N": 0.49
  },
  "KVS0425": {
    "O": 0.25,
    "C": 0.23,
    "E": 0.28,
    "A": 0.5,
    "N": 0.6
  },
  "AJR0319": {
    "O": 0.75,
    "C": 0.07,
    "E": 0.68,
    "A": 0.15,
    "N": 0.29
  },
  "DLS0383": {
    "O": 0.0,
    "C": 0.28,
    "E": 0.05,
    "A": 0.38,
    "N": 0.29
  },
  "BCR0581": {
    "O": 0.25,
    "C": 0.03,
    "E": 0.6,
    "A": 0.65,
    "N": 0.46
  },
  "LDB0090": {
    "O": 0.75,
    "C": 0.1,
    "E": 0.73,
    "A": 0.78,
    "N": 0.57
  },
  "GAF0570": {
    "O": 0.53,
    "C": 0.12,
    "E": 0.7,
    "A": 0.9,
    "N": 0.6
  },
  "NNS0059": {
    "O": 0.8,
    "C": 0.33,
    "E": 0.95,
    "A": 0.33,
    "N": 0.31
  },
  "JRL0574": {
    "O": 0.23,
    "C": 0.4,
    "E": 0.62,
    "A": 0.93,
    "N": 0.74
  },
  "NSS0876": {
    "O": 0.4,
    "C": 0.25,
    "E": 0.38,
    "A": 0.8,
    "N": 0.49
  },
  "SOB0586": {
    "O": 0.88,
    "C": 0.62,
    "E": 0.33,
    "A": 0.35,
    "N": 0.46
  },
  "DDA0476": {
    "O": 0.65,
    "C": 0.38,
    "E": 0.73,
    "A": 0.07,
    "N": 0.71
  },
  "DEB0782": {
    "O": 0.8,
    "C": 0.93,
    "E": 0.55,
    "A": 0.28,
    "N": 0.63
  },
  "OLW0689": {
    "O": 0.3,
    "C": 0.38,
    "E": 0.75,
    "A": 0.62,
    "N": 0.37
  },
  "MMG0943": {
    "O": 0.33,
    "C": 0.42,
    "E": 0.45,
    "A": 0.6,
    "N": 0.34
  },
  "RNL0695": {
    "O": 0.93,
    "C": 0.78,
    "E": 0.85,
    "A": 0.23,
    "N": 0.63
  },
  "LNR0656": {
    "O": 0.38,
    "C": 0.73,
    "E": 0.05,
    "A": 0.5,
    "N": 0.26
  },
  "AMJ0297": {
    "O": 0.15,
    "C": 0.82,
    "E": 1.0,
    "A": 0.2,
    "N": 0.4
  },
  "HRL0540": {
    "O": 0.82,
    "C": 0.7,
    "E": 0.17,
    "A": 0.75,
    "N": 0.11
  },
  "DLF0377": {
    "O": 0.73,
    "C": 0.62,
    "E": 0.23,
    "A": 0.42,
    "N": 0.57
  },
  "MVH0373": {
    "O": 0.85,
    "C": 0.23,
    "E": 0.25,
    "A": 0.28,
    "N": 0.31
  },
  "TPH0474": {
    "O": 0.85,
    "C": 0.73,
    "E": 0.1,
    "A": 0.28,
    "N": 0.6
  },
  "KCF0045": {
    "O": 0.75,
    "C": 0.73,
    "E": 0.15,
    "A": 0.42,
    "N": 0.49
  },
  "BIS0247": {
    "O": 0.65,
    "C": 0.23,
    "E": 0.2,
    "A": 0.73,
    "N": 0.66
  },
  "MSS0001": {
    "O": 0.28,
    "C": 0.85,
    "E": 0.35,
    "A": 0.88,
    "N": 0.14
  },
  "EFS0882": {
    "O": 0.75,
    "C": 0.75,
    "E": 0.93,
    "A": 0.38,
    "N": 0.37
  },
  "NWK0215": {
    "O": 0.28,
    "C": 0.23,
    "E": 0.88,
    "A": 0.2,
    "N": 0.29
  },
  "PNL0301": {
    "O": 1.0,
    "C": 0.82,
    "E": 0.5,
    "A": 0.82,
    "N": 0.49
  },
  "CSH0626": {
    "O": 0.58,
    "C": 0.17,
    "E": 0.78,
    "A": 0.2,
    "N": 0.26
  },
  "BHW0458": {
    "O": 0.65,
    "C": 0.55,
    "E": 0.45,
    "A": 0.5,
    "N": 0.43
  },
  "SSH0799": {
    "O": 0.33,
    "C": 0.2,
    "E": 0.53,
    "A": 0.53,
    "N": 0.74
  },
  "ANM0123": {
    "O": 0.3,
    "C": 0.12,
    "E": 0.15,
    "A": 0.28,
    "N": 0.34
  },
  "CAS0507": {
    "O": 0.1,
    "C": 0.9,
    "E": 0.58,
    "A": 0.03,
    "N": 0.31
  },
  "DID0650": {
    "O": 0.88,
    "C": 0.28,
    "E": 0.17,
    "A": 0.8,
    "N": 0.2
  },
  "KAT0270": {
    "O": 0.28,
    "C": 0.35,
    "E": 0.73,
    "A": 0.33,
    "N": 0.37
  },
  "TEM0977": {
    "O": 0.3,
    "C": 0.23,
    "E": 0.75,
    "A": 0.88,
    "N": 0.43
  },
  "SHR0334": {
    "O": 0.65,
    "C": 0.78,
    "E": 0.88,
    "A": 0.23,
    "N": 0.49
  },
  "JDC0030": {
    "O": 0.53,
    "C": 0.2,
    "E": 0.23,
    "A": 0.28,
    "N": 0.34
  },
  "CKP0721": {
    "O": 0.75,
    "C": 0.73,
    "E": 0.73,
    "A": 0.07,
    "N": 0.51
  },
  "HIA0414": {
    "O": 0.7,
    "C": 0.73,
    "E": 0.73,
    "A": 0.2,
    "N": 0.49
  },
  "HSP0290": {
    "O": 0.7,
    "C": 0.12,
    "E": 0.45,
    "A": 0.25,
    "N": 0.37
  },
  "HRW0550": {
    "O": 0.7,
    "C": 0.6,
    "E": 0.35,
    "A": 0.3,
    "N": 0.4
  },
  "KBB0189": {
    "O": 0.97,
    "C": 0.33,
    "E": 0.15,
    "A": 0.58,
    "N": 0.46
  },
  "CBB0365": {
    "O": 0.68,
    "C": 0.17,
    "E": 0.25,
    "A": 0.78,
    "N": 0.54
  },
  "DLH0029": {
    "O": 0.65,
    "C": 0.4,
    "E": 0.7,
    "A": 0.2,
    "N": 0.49
  },
  "NRO0768": {
    "O": 0.2,
    "C": 0.2,
    "E": 0.78,
    "A": 0.38,
    "N": 0.63
  },
  "NWT0098": {
    "O": 0.62,
    "C": 0.73,
    "E": 0.4,
    "A": 0.65,
    "N": 0.54
  },
  "QPM0727": {
    "O": 0.82,
    "C": 0.75,
    "E": 0.2,
    "A": 0.6,
    "N": 0.57
  },
  "KVT0028": {
    "O": 0.85,
    "C": 0.25,
    "E": 0.62,
    "A": 0.23,
    "N": 0.66
  },
  "LFS0071": {
    "O": 0.95,
    "C": 0.53,
    "E": 0.1,
    "A": 0.17,
    "N": 0.31
  },
  "WNB0908": {
    "O": 0.7,
    "C": 0.7,
    "E": 0.7,
    "A": 0.3,
    "N": 0.26
  },
  "PAD0773": {
    "O": 0.65,
    "C": 0.28,
    "E": 0.1,
    "A": 0.15,
    "N": 0.69
  },
  "BJH0354": {
    "O": 0.3,
    "C": 0.28,
    "E": 0.53,
    "A": 0.25,
    "N": 0.63
  },
  "ONW0083": {
    "O": 0.9,
    "C": 0.5,
    "E": 0.38,
    "A": 0.5,
    "N": 0.34
  },
  "SSJ0784": {
    "O": 0.23,
    "C": 0.73,
    "E": 0.05,
    "A": 0.88,
    "N": 0.57
  },
  "KJP0371": {
    "O": 0.65,
    "C": 0.28,
    "E": 0.38,
    "A": 0.12,
    "N": 0.46
  },
  "IMB0481": {
    "O": 0.23,
    "C": 0.78,
    "E": 0.7,
    "A": 0.82,
    "N": 0.69
  },
  "BQS0525": {
    "O": 0.8,
    "C": 0.7,
    "E": 0.23,
    "A": 0.88,
    "N": 0.46
  },
  "BTR0403": {
    "O": 0.93,
    "C": 0.93,
    "E": 0.28,
    "A": 0.17,
    "N": 0.4
  },
  "DLM0051": {
    "O": 0.68,
    "C": 0.68,
    "E": 0.17,
    "A": 0.25,
    "N": 0.6
  },
  "AHM0410": {
    "O": 0.6,
    "C": 0.82,
    "E": 0.12,
    "A": 0.2,
    "N": 0.34
  },
  "CHM0821": {
    "O": 0.95,
    "C": 0.03,
    "E": 0.73,
    "A": 0.23,
    "N": 0.26
  },
  "JBM0350": {
    "O": 0.68,
    "C": 0.28,
    "E": 0.05,
    "A": 0.88,
    "N": 0.31
  },
  "JRG0207": {
    "O": 0.8,
    "C": 0.68,
    "E": 0.75,
    "A": 0.28,
    "N": 0.37
  },
  "PLH0862": {
    "O": 0.55,
    "C": 0.68,
    "E": 0.38,
    "A": 0.15,
    "N": 0.51
  },
  "RCP0785": {
    "O": 0.8,
    "C": 0.7,
    "E": 0.82,
    "A": 0.5,
    "N": 0.51
  },
  "NSC0597": {
    "O": 0.23,
    "C": 0.07,
    "E": 0.03,
    "A": 0.85,
    "N": 0.49
  },
  "AVM0947": {
    "O": 0.0,
    "C": 0.38,
    "E": 0.5,
    "A": 0.85,
    "N": 0.71
  },
  "MSZ0310": {
    "O": 0.35,
    "C": 0.7,
    "E": 0.2,
    "A": 0.53,
    "N": 0.43
  },
  "SDB0106": {
    "O": 0.62,
    "C": 0.9,
    "E": 0.4,
    "A": 0.42,
    "N": 0.66
  },
  "HAC0282": {
    "O": 0.68,
    "C": 0.55,
    "E": 0.7,
    "A": 0.05,
    "N": 0.4
  },
  "HSB0196": {
    "O": 0.85,
    "C": 0.07,
    "E": 0.82,
    "A": 0.5,
    "N": 0.54
  },
  "ASB0796": {
    "O": 0.5,
    "C": 0.75,
    "E": 0.33,
    "A": 0.7,
    "N": 0.57
  },
  "WRM0963": {
    "O": 0.17,
    "C": 0.33,
    "E": 0.82,
    "A": 0.53,
    "N": 0.23
  },
  "BRM0995": {
    "O": 0.25,
    "C": 0.03,
    "E": 0.55,
    "A": 0.4,
    "N": 0.74
  },
  "SES0477": {
    "O": 0.7,
    "C": 0.75,
    "E": 0.07,
    "A": 0.73,
    "N": 0.43
  },
  "JTM0223": {
    "O": 0.62,
    "C": 0.95,
    "E": 0.25,
    "A": 0.28,
    "N": 0.46
  },
  "RNF0765": {
    "O": 0.78,
    "C": 0.3,
    "E": 0.68,
    "A": 0.78,
    "N": 0.31
  },
  "GNZ0953": {
    "O": 0.4,
    "C": 0.2,
    "E": 0.4,
    "A": 0.65,
    "N": 0.43
  },
  "HRB0351": {
    "O": 0.23,
    "C": 0.05,
    "E": 0.82,
    "A": 0.8,
    "N": 0.63
  },
  "ZSB0649": {
    "O": 0.33,
    "C": 0.38,
    "E": 0.65,
    "A": 0.1,
    "N": 0.34
  },
  "ADC0391": {
    "O": 1.0,
    "C": 0.82,
    "E": 0.75,
    "A": 0.58,
    "N": 0.69
  },
  "PMC0328": {
    "O": 0.25,
    "C": 0.82,
    "E": 0.0,
    "A": 0.65,
    "N": 0.54
  },
  "ILJ0526": {
    "O": 0.58,
    "C": 1.0,
    "E": 0.33,
    "A": 0.9,
    "N": 0.31
  },
  "ANT0430": {
    "O": 0.05,
    "C": 0.23,
    "E": 0.33,
    "A": 0.95,
    "N": 0.49
  },
  "DFH0188": {
    "O": 0.62,
    "C": 0.75,
    "E": 0.2,
    "A": 0.7,
    "N": 0.29
  },
  "LLV0602": {
    "O": 0.65,
    "C": 0.0,
    "E": 0.65,
    "A": 0.68,
    "N": 0.54
  },
  "GCR0554": {
    "O": 0.15,
    "C": 0.15,
    "E": 0.78,
    "A": 0.33,
    "N": 0.66
  },
  "SJO0209": {
    "O": 0.73,
    "C": 0.88,
    "E": 0.2,
    "A": 0.73,
    "N": 0.6
  },
  "NGC0058": {
    "O": 0.85,
    "C": 0.88,
    "E": 0.73,
    "A": 0.12,
    "N": 0.37
  },
  "YIC0195": {
    "O": 0.2,
    "C": 0.97,
    "E": 0.23,
    "A": 0.75,
    "N": 0.49
  },
  "EDB0714": {
    "O": 0.28,
    "C": 0.33,
    "E": 0.62,
    "A": 0.4,
    "N": 0.43
  },
  "LHL0309": {
    "O": 0.23,
    "C": 0.6,
    "E": 0.42,
    "A": 0.9,
    "N": 0.66
  },
  "HFB0347": {
    "O": 0.6,
    "C": 0.25,
    "E": 0.5,
    "A": 0.5,
    "N": 0.37
  },
  "EJW0884": {
    "O": 0.9,
    "C": 0.25,
    "E": 0.55,
    "A": 0.4,
    "N": 0.49
  },
  "CRO0027": {
    "O": 0.23,
    "C": 0.5,
    "E": 0.45,
    "A": 0.9,
    "N": 0.34
  },
  "HKR0628": {
    "O": 0.28,
    "C": 0.15,
    "E": 0.17,
    "A": 0.15,
    "N": 0.31
  },
  "GTD0116": {
    "O": 0.82,
    "C": 0.23,
    "E": 0.88,
    "A": 0.25,
    "N": 0.49
  },
  "DSB0731": {
    "O": 0.4,
    "C": 0.12,
    "E": 0.75,
    "A": 0.82,
    "N": 0.46
  },
  "COF0120": {
    "O": 0.1,
    "C": 0.05,
    "E": 0.7,
    "A": 0.07,
    "N": 0.6
  },
  "HDJ0446": {
    "O": 0.2,
    "C": 0.17,
    "E": 0.88,
    "A": 0.42,
    "N": 0.6
  },
  "CHG0146": {
    "O": 0.75,
    "C": 0.25,
    "E": 0.73,
    "A": 0.23,
    "N": 0.6
  },
  "AIH0675": {
    "O": 0.38,
    "C": 0.73,
    "E": 0.7,
    "A": 0.75,
    "N": 0.66
  },
  "TNM0961": {
    "O": 0.68,
    "C": 1.0,
    "E": 0.73,
    "A": 0.17,
    "N": 0.51
  },
  "APG0307": {
    "O": 0.82,
    "C": 0.73,
    "E": 0.65,
    "A": 0.82,
    "N": 0.23
  },
  "RHC0335": {
    "O": 0.65,
    "C": 0.62,
    "E": 0.75,
    "A": 0.9,
    "N": 0.31
  },
  "CQW0652": {
    "O": 0.0,
    "C": 0.3,
    "E": 0.95,
    "A": 0.25,
    "N": 0.54
  },
  "HJS0072": {
    "O": 0.85,
    "C": 0.8,
    "E": 0.23,
    "A": 0.23,
    "N": 0.49
  },
  "XHW0498": {
    "O": 0.68,
    "C": 0.93,
    "E": 0.95,
    "A": 0.33,
    "N": 0.6
  },
  "IJW0851": {
    "O": 0.28,
    "C": 0.0,
    "E": 0.0,
    "A": 0.2,
    "N": 0.57
  },
  "NAR0981": {
    "O": 0.73,
    "C": 0.73,
    "E": 0.15,
    "A": 1.0,
    "N": 0.63
  },
  "NUL0471": {
    "O": 0.62,
    "C": 0.7,
    "E": 0.7,
    "A": 0.4,
    "N": 0.66
  },
  "DIB0081": {
    "O": 0.6,
    "C": 0.88,
    "E": 0.1,
    "A": 0.45,
    "N": 0.54
  },
  "BSS0369": {
    "O": 0.73,
    "C": 0.8,
    "E": 0.6,
    "A": 0.1,
    "N": 0.51
  },
  "MIB0904": {
    "O": 0.3,
    "C": 0.28,
    "E": 0.6,
    "A": 0.7,
    "N": 0.31
  },
  "AAF0535": {
    "O": 0.17,
    "C": 0.28,
    "E": 0.65,
    "A": 0.58,
    "N": 0.49
  },
  "HBB0056": {
    "O": 0.68,
    "C": 0.58,
    "E": 0.5,
    "A": 0.28,
    "N": 0.37
  },
  "MCJ0324": {
    "O": 0.45,
    "C": 0.25,
    "E": 0.75,
    "A": 0.25,
    "N": 0.63
  },
  "HDH0928": {
    "O": 0.75,
    "C": 0.65,
    "E": 0.25,
    "A": 0.75,
    "N": 0.34
  },
  "HXL0968": {
    "O": 0.88,
    "C": 0.28,
    "E": 0.62,
    "A": 0.75,
    "N": 0.57
  },
  "MOH0273": {
    "O": 0.73,
    "C": 0.75,
    "E": 0.93,
    "A": 1.0,
    "N": 0.34
  },
  "KNW0644": {
    "O": 0.12,
    "C": 0.25,
    "E": 0.33,
    "A": 0.12,
    "N": 0.31
  },
  "CGA0629": {
    "O": 0.65,
    "C": 0.62,
    "E": 0.35,
    "A": 0.97,
    "N": 0.4
  },
  "NMS0280": {
    "O": 0.73,
    "C": 0.8,
    "E": 0.4,
    "A": 0.68,
    "N": 0.37
  },
  "THD0448": {
    "O": 0.78,
    "C": 0.55,
    "E": 0.48,
    "A": 0.7,
    "N": 0.51
  },
  "SPA0141": {
    "O": 0.82,
    "C": 0.3,
    "E": 0.0,
    "A": 0.28,
    "N": 0.43
  },
  "LPC0492": {
    "O": 0.5,
    "C": 0.33,
    "E": 0.3,
    "A": 0.5,
    "N": 0.34
  },
  "BTN0061": {
    "O": 0.8,
    "C": 0.28,
    "E": 0.3,
    "A": 0.25,
    "N": 0.23
  },
  "HGH0595": {
    "O": 0.78,
    "C": 0.1,
    "E": 0.3,
    "A": 0.73,
    "N": 0.43
  },
  "BAM0611": {
    "O": 0.38,
    "C": 0.5,
    "E": 0.73,
    "A": 0.33,
    "N": 0.31
  },
  "KKC0683": {
    "O": 0.55,
    "C": 0.68,
    "E": 0.68,
    "A": 0.95,
    "N": 0.6
  },
  "BBS0422": {
    "O": 0.73,
    "C": 0.8,
    "E": 0.48,
    "A": 0.78,
    "N": 0.11
  },
  "HDL0748": {
    "O": 0.38,
    "C": 0.07,
    "E": 0.9,
    "A": 0.78,
    "N": 0.31
  },
  "NRD0548": {
    "O": 0.78,
    "C": 0.68,
    "E": 0.78,
    "A": 0.12,
    "N": 0.49
  },
  "DCC0160": {
    "O": 0.65,
    "C": 0.73,
    "E": 0.58,
    "A": 0.8,
    "N": 0.37
  },
  "MES0407": {
    "O": 0.7,
    "C": 0.85,
    "E": 0.38,
    "A": 0.93,
    "N": 0.66
  },
  "LMF0980": {
    "O": 0.8,
    "C": 0.88,
    "E": 0.05,
    "A": 0.85,
    "N": 0.6
  },
  "BMM0112": {
    "O": 0.75,
    "C": 0.65,
    "E": 0.35,
    "A": 0.75,
    "N": 0.31
  },
  "LTS0860": {
    "O": 0.95,
    "C": 0.25,
    "E": 0.48,
    "A": 0.25,
    "N": 0.49
  },
  "AOK0844": {
    "O": 0.03,
    "C": 0.5,
    "E": 0.85,
    "A": 0.4,
    "N": 0.49
  },
  "ESJ0670": {
    "O": 0.8,
    "C": 0.53,
    "E": 0.12,
    "A": 0.75,
    "N": 0.29
  },
  "AAF0791": {
    "O": 0.1,
    "C": 0.75,
    "E": 0.75,
    "A": 1.0,
    "N": 0.57
  },
  "KRL0501": {
    "O": 0.2,
    "C": 0.42,
    "E": 0.33,
    "A": 0.45,
    "N": 0.34
  },
  "SAC0592": {
    "O": 0.35,
    "C": 0.2,
    "E": 0.33,
    "A": 0.8,
    "N": 0.34
  },
  "UCS0227": {
    "O": 0.3,
    "C": 0.55,
    "E": 0.78,
    "A": 0.62,
    "N": 0.57
  },
  "JCR0770": {
    "O": 0.75,
    "C": 0.93,
    "E": 0.35,
    "A": 0.28,
    "N": 0.37
  },
  "ICS0956": {
    "O": 0.3,
    "C": 0.25,
    "E": 0.2,
    "A": 0.62,
    "N": 0.34
  },
  "MKW0441": {
    "O": 0.12,
    "C": 0.38,
    "E": 0.88,
    "A": 0.25,
    "N": 0.57
  },
  "TSM0927": {
    "O": 0.58,
    "C": 0.28,
    "E": 0.0,
    "A": 0.68,
    "N": 0.34
  },
  "OJK0233": {
    "O": 0.75,
    "C": 0.65,
    "E": 0.1,
    "A": 0.3,
    "N": 0.54
  },
  "SMW0084": {
    "O": 0.25,
    "C": 0.68,
    "E": 0.73,
    "A": 0.95,
    "N": 0.37
  },
  "BEH0615": {
    "O": 0.35,
    "C": 0.25,
    "E": 1.0,
    "A": 0.3,
    "N": 0.34
  },
  "ADF0397": {
    "O": 0.73,
    "C": 0.15,
    "E": 0.0,
    "A": 0.75,
    "N": 0.6
  },
  "NJC0705": {
    "O": 0.82,
    "C": 0.73,
    "E": 0.48,
    "A": 0.65,
    "N": 0.49
  },
  "BYP0070": {
    "O": 0.5,
    "C": 0.23,
    "E": 0.78,
    "A": 0.28,
    "N": 0.54
  },
  "JMD0520": {
    "O": 0.28,
    "C": 0.88,
    "E": 0.15,
    "A": 0.7,
    "N": 0.43
  },
  "LAF0991": {
    "O": 0.75,
    "C": 0.73,
    "E": 0.65,
    "A": 0.3,
    "N": 0.57
  },
  "KBS0874": {
    "O": 0.33,
    "C": 0.73,
    "E": 0.68,
    "A": 0.58,
    "N": 0.43
  },
  "GHH0288": {
    "O": 0.05,
    "C": 0.65,
    "E": 0.75,
    "A": 0.65,
    "N": 0.46
  },
  "TAC0300": {
    "O": 0.12,
    "C": 0.7,
    "E": 0.2,
    "A": 0.2,
    "N": 0.63
  },
  "JAJ0849": {
    "O": 0.3,
    "C": 0.35,
    "E": 0.33,
    "A": 0.33,
    "N": 0.54
  },
  "NOB0181": {
    "O": 0.53,
    "C": 0.28,
    "E": 0.28,
    "A": 0.78,
    "N": 0.31
  },
  "DTP0379": {
    "O": 0.88,
    "C": 0.8,
    "E": 0.12,
    "A": 0.68,
    "N": 0.37
  },
  "CJM0138": {
    "O": 0.0,
    "C": 0.75,
    "E": 0.28,
    "A": 0.17,
    "N": 0.26
  },
  "FHS0837": {
    "O": 0.33,
    "C": 0.68,
    "E": 0.1,
    "A": 0.8,
    "N": 0.57
  },
  "CAA0612": {
    "O": 0.25,
    "C": 0.78,
    "E": 0.55,
    "A": 0.8,
    "N": 0.49
  },
  "ELT0769": {
    "O": 0.23,
    "C": 0.25,
    "E": 0.25,
    "A": 0.42,
    "N": 0.6
  },
  "KJW0416": {
    "O": 1.0,
    "C": 0.9,
    "E": 0.73,
    "A": 0.78,
    "N": 0.46
  },
  "CTR0341": {
    "O": 0.88,
    "C": 0.73,
    "E": 0.33,
    "A": 0.07,
    "N": 0.4
  },
  "DIC0988": {
    "O": 0.85,
    "C": 0.5,
    "E": 0.33,
    "A": 0.28,
    "N": 0.51
  },
  "JJH0292": {
    "O": 0.62,
    "C": 0.33,
    "E": 0.7,
    "A": 0.73,
    "N": 0.4
  },
  "MJS0890": {
    "O": 0.0,
    "C": 0.4,
    "E": 0.15,
    "A": 0.03,
    "N": 0.43
  },
  "TOR0193": {
    "O": 0.5,
    "C": 0.75,
    "E": 0.38,
    "A": 0.88,
    "N": 0.46
  },
  "SCB0534": {
    "O": 0.25,
    "C": 0.2,
    "E": 0.62,
    "A": 0.3,
    "N": 0.43
  },
  "MDH0686": {
    "O": 0.68,
    "C": 0.82,
    "E": 0.53,
    "A": 0.25,
    "N": 0.69
  },
  "JOM0750": {
    "O": 0.62,
    "C": 0.9,
    "E": 0.38,
    "A": 0.75,
    "N": 0.43
  },
  "BRB0355": {
    "O": 0.58,
    "C": 0.28,
    "E": 0.68,
    "A": 0.23,
    "N": 0.43
  },
  "MJM0510": {
    "O": 0.55,
    "C": 0.58,
    "E": 0.3,
    "A": 0.2,
    "N": 0.71
  },
  "KJM0887": {
    "O": 0.53,
    "C": 0.93,
    "E": 0.1,
    "A": 0.15,
    "N": 0.51
  },
  "CBG0398": {
    "O": 0.75,
    "C": 0.28,
    "E": 0.78,
    "A": 0.0,
    "N": 0.29
  },
  "RRC0553": {
    "O": 0.75,
    "C": 0.1,
    "E": 0.35,
    "A": 0.7,
    "N": 0.43
  },
  "TDS0984": {
    "O": 0.73,
    "C": 0.73,
    "E": 0.12,
    "A": 0.75,
    "N": 0.69
  },
  "LRR0148": {
    "O": 0.28,
    "C": 0.23,
    "E": 0.1,
    "A": 0.1,
    "N": 0.43
  },
  "ARB0834": {
    "O": 0.75,
    "C": 0.8,
    "E": 0.75,
    "A": 0.97,
    "N": 0.34
  },
  "KPC0073": {
    "O": 0.85,
    "C": 0.5,
    "E": 0.03,
    "A": 0.15,
    "N": 0.26
  },
  "CLB0774": {
    "O": 0.97,
    "C": 0.33,
    "E": 0.3,
    "A": 0.17,
    "N": 0.49
  },
  "VEB0935": {
    "O": 0.9,
    "C": 0.68,
    "E": 0.73,
    "A": 0.25,
    "N": 0.51
  },
  "MCT0720": {
    "O": 0.6,
    "C": 0.05,
    "E": 0.25,
    "A": 0.3,
    "N": 0.66
  },
  "JDF0593": {
    "O": 0.5,
    "C": 0.88,
    "E": 0.03,
    "A": 0.78,
    "N": 0.43
  },
  "CJG0470": {
    "O": 0.85,
    "C": 0.88,
    "E": 0.3,
    "A": 0.55,
    "N": 0.29
  },
  "RGG0064": {
    "O": 0.65,
    "C": 0.23,
    "E": 0.25,
    "A": 0.8,
    "N": 0.57
  },
  "BXJ0010": {
    "O": 0.9,
    "C": 0.35,
    "E": 0.5,
    "A": 0.62,
    "N": 0.57
  },
  "WBC0315": {
    "O": 0.75,
    "C": 0.68,
    "E": 0.75,
    "A": 0.88,
    "N": 0.29
  },
  "CGB0637": {
    "O": 0.25,
    "C": 0.25,
    "E": 0.12,
    "A": 0.25,
    "N": 0.43
  },
  "CAN0842": {
    "O": 0.7,
    "C": 0.78,
    "E": 0.3,
    "A": 0.73,
    "N": 0.43
  },
  "HTH0007": {
    "O": 0.68,
    "C": 0.7,
    "E": 0.78,
    "A": 0.25,
    "N": 0.63
  },
  "BJM0111": {
    "O": 0.3,
    "C": 0.35,
    "E": 0.73,
    "A": 0.78,
    "N": 0.14
  },
  "MAW0166": {
    "O": 0.85,
    "C": 0.15,
    "E": 0.28,
    "A": 0.17,
    "N": 0.57
  },
  "PPF0435": {
    "O": 0.8,
    "C": 0.17,
    "E": 0.95,
    "A": 0.35,
    "N": 0.37
  },
  "SEJ0677": {
    "O": 0.85,
    "C": 0.73,
    "E": 0.33,
    "A": 0.65,
    "N": 0.31
  },
  "ACV0812": {
    "O": 0.8,
    "C": 0.68,
    "E": 0.05,
    "A": 0.88,
    "N": 0.4
  },
  "KWE0082": {
    "O": 0.7,
    "C": 0.82,
    "E": 0.23,
    "A": 0.95,
    "N": 0.6
  },
  "ECL0930": {
    "O": 0.45,
    "C": 0.35,
    "E": 0.75,
    "A": 0.2,
    "N": 0.43
  },
  "RHP0484": {
    "O": 0.62,
    "C": 0.68,
    "E": 0.35,
    "A": 0.15,
    "N": 0.49
  },
  "BAM0636": {
    "O": 0.07,
    "C": 0.75,
    "E": 0.9,
    "A": 0.8,
    "N": 0.71
  },
  "DDM0579": {
    "O": 0.58,
    "C": 0.88,
    "E": 0.5,
    "A": 0.68,
    "N": 0.34
  },
  "UIR0043": {
    "O": 0.23,
    "C": 0.68,
    "E": 0.33,
    "A": 0.7,
    "N": 0.51
  },
  "JCR0172": {
    "O": 0.82,
    "C": 0.78,
    "E": 0.78,
    "A": 0.73,
    "N": 0.49
  },
  "ATE0869": {
    "O": 0.07,
    "C": 0.12,
    "E": 0.75,
    "A": 0.85,
    "N": 0.54
  },
  "IBS0836": {
    "O": 0.0,
    "C": 0.85,
    "E": 1.0,
    "A": 0.7,
    "N": 0.37
  },
  "DTT0076": {
    "O": 0.8,
    "C": 0.15,
    "E": 0.6,
    "A": 0.35,
    "N": 0.4
  },
  "PRM0740": {
    "O": 0.88,
    "C": 0.75,
    "E": 0.88,
    "A": 0.8,
    "N": 0.37
  },
  "FGW0853": {
    "O": 0.38,
    "C": 0.62,
    "E": 0.25,
    "A": 0.75,
    "N": 0.71
  },
  "JSH0330": {
    "O": 0.25,
    "C": 0.15,
    "E": 0.33,
    "A": 0.35,
    "N": 0.4
  },
  "FSB0399": {
    "O": 0.33,
    "C": 0.3,
    "E": 0.12,
    "A": 0.68,
    "N": 0.34
  }
}